Workbook

Sheet Pagina de busca
H1: By.Isaque M.D.P
H2: Aperte Ctrl - | I2: <- para poder enxergar mais informações
A5: BP: | H5: <--- Clicar no vermelho e apertar "Espaço+Enter" para esvaziar.
A6: NOME | B6: {=INDEX(AF:AF, MATCH(B5, AA:AA, 0))} -> #N/A
A7: MOTIVO CALL:
A8: PNR
A9: NOTA:
A10: COMENTÁRIO:
A13: ASSIM QUE PREENCHER TUDO E DER 'ENTER' AGUARDE 3 Segundos
A14: LINKS DOS ATENDIMENTOS
A16: PRIMEIRO LINK -> | C16: ='Pagina de sistema'!F2 -> https://docs.google.com/forms/d/e/1FAIpQLSdL6XnoqNKTAw7dlsIr2ZZmRPtlLw-idLKWanRUaG1h56cebg/viewform?entry.1095270279=&entry.191341224=&entry.2101494904=Dúvida&entry.1095270279=&entry.950207260=&entry.237710686=&entry.1585267062=&entry.409012661= | G16: ='Pagina de sistema'!C2 | H16: ='Pagina de sistema'!B2
A17: SOMENTE CLICAR -> | C17: ='Pagina de sistema'!F3 -> https://docs.google.com/forms/d/e/1FAIpQLSdL6XnoqNKTAw7dlsIr2ZZmRPtlLw-idLKWanRUaG1h56cebg/viewform?entry.1095270279=&entry.191341224=&entry.2101494904=Dúvida&entry.1095270279=&entry.950207260=&entry.237710686=&entry.1585267062=&entry.409012661= | G17: ='Pagina de sistema'!C3 | H17: ='Pagina de sistema'!B3
A18: SOMENTE CLICAR -> | C18: ='Pagina de sistema'!F4 -> https://docs.google.com/forms/d/e/1FAIpQLSdL6XnoqNKTAw7dlsIr2ZZmRPtlLw-idLKWanRUaG1h56cebg/viewform?entry.1095270279=&entry.191341224=&entry.2101494904=Dúvida&entry.1095270279=&entry.950207260=&entry.237710686=&entry.1585267062=&entry.409012661= | G18: ='Pagina de sistema'!C4 | H18: ='Pagina de sistema'!B4
A19: SOMENTE CLICAR -> | C19: ='Pagina de sistema'!F5 -> https://docs.google.com/forms/d/e/1FAIpQLSdL6XnoqNKTAw7dlsIr2ZZmRPtlLw-idLKWanRUaG1h56cebg/viewform?entry.1095270279=&entry.191341224=&entry.2101494904=Dúvida&entry.1095270279=&entry.950207260=&entry.237710686=&entry.1585267062=&entry.409012661= | G19: ='Pagina de sistema'!C5 | H19: ='Pagina de sistema'!B5
A20: SOMENTE CLICAR -> | C20: ='Pagina de sistema'!F6 -> https://docs.google.com/forms/d/e/1FAIpQLSdL6XnoqNKTAw7dlsIr2ZZmRPtlLw-idLKWanRUaG1h56cebg/viewform?entry.1095270279=&entry.191341224=&entry.2101494904=Dúvida&entry.1095270279=&entry.950207260=&entry.237710686=&entry.1585267062=&entry.409012661= | G20: ='Pagina de sistema'!C6 | H20: ='Pagina de sistema'!B6
A21: SOMENTE CLICAR -> | C21: ='Pagina de sistema'!F7 -> https://docs.google.com/forms/d/e/1FAIpQLSdL6XnoqNKTAw7dlsIr2ZZmRPtlLw-idLKWanRUaG1h56cebg/viewform?entry.1095270279=&entry.191341224=&entry.2101494904=Dúvida&entry.1095270279=&entry.950207260=&entry.237710686=&entry.1585267062=&entry.409012661= | G21: ='Pagina de sistema'!C7 | H21: ='Pagina de sistema'!B7
A22: SOMENTE CLICAR -> | C22: ='Pagina de sistema'!F8 -> https://docs.google.com/forms/d/e/1FAIpQLSdL6XnoqNKTAw7dlsIr2ZZmRPtlLw-idLKWanRUaG1h56cebg/viewform?entry.1095270279=&entry.191341224=&entry.2101494904=Dúvida&entry.1095270279=&entry.950207260=&entry.237710686=&entry.1585267062=&entry.409012661= | G22: ='Pagina de sistema'!C8 | H22: ='Pagina de sistema'!B8
A23: SOMENTE CLICAR -> | C23: ='Pagina de sistema'!F9 -> https://docs.google.com/forms/d/e/1FAIpQLSdL6XnoqNKTAw7dlsIr2ZZmRPtlLw-idLKWanRUaG1h56cebg/viewform?entry.1095270279=&entry.191341224=&entry.2101494904=Dúvida&entry.1095270279=&entry.950207260=&entry.237710686=&entry.1585267062=&entry.409012661= | G23: ='Pagina de sistema'!C9 | H23: ='Pagina de sistema'!B9
A24: SOMENTE CLICAR -> | C24: ='Pagina de sistema'!F10 -> https://docs.google.com/forms/d/e/1FAIpQLSdL6XnoqNKTAw7dlsIr2ZZmRPtlLw-idLKWanRUaG1h56cebg/viewform?entry.1095270279=&entry.191341224=&entry.2101494904=Dúvida&entry.1095270279=&entry.950207260=&entry.237710686=&entry.1585267062=&entry.409012661= | G24: ='Pagina de sistema'!C10 | H24: ='Pagina de sistema'!B10
A25: SOMENTE CLICAR -> | C25: ='Pagina de sistema'!F11 -> https://docs.google.com/forms/d/e/1FAIpQLSdL6XnoqNKTAw7dlsIr2ZZmRPtlLw-idLKWanRUaG1h56cebg/viewform?entry.1095270279=&entry.191341224=&entry.2101494904=Dúvida&entry.1095270279=&entry.950207260=&entry.237710686=&entry.1585267062=&entry.409012661= | G25: ='Pagina de sistema'!C11 | H25: ='Pagina de sistema'!B11
A26: SOMENTE CLICAR -> | C26: ='Pagina de sistema'!F12 -> https://docs.google.com/forms/d/e/1FAIpQLSdL6XnoqNKTAw7dlsIr2ZZmRPtlLw-idLKWanRUaG1h56cebg/viewform?entry.1095270279=&entry.191341224=&entry.2101494904=Dúvida&entry.1095270279=&entry.950207260=&entry.237710686=&entry.1585267062=&entry.409012661= | G26: ='Pagina de sistema'!C12 | H26: ='Pagina de sistema'!B12
A27: SOMENTE CLICAR -> | C27: ='Pagina de sistema'!F13 -> https://docs.google.com/forms/d/e/1FAIpQLSdL6XnoqNKTAw7dlsIr2ZZmRPtlLw-idLKWanRUaG1h56cebg/viewform?entry.1095270279=&entry.191341224=&entry.2101494904=Dúvida&entry.1095270279=&entry.950207260=&entry.237710686=&entry.1585267062=&entry.409012661= | G27: ='Pagina de sistema'!C13 | H27: ='Pagina de sistema'!B13
... A368: SOMENTE CLICAR -> | C368: ='Pagina de sistema'!F354 -> https://docs.google.com/forms/d/e/1FAIpQLSdL6XnoqNKTAw7dlsIr2ZZmRPtlLw-idLKWanRUaG1h56cebg/viewform?entry.1095270279=&entry.191341224=&entry.2101494904=Dúvida&entry.1095270279=&entry.950207260=&entry.237710686=&entry.1585267062=&entry.409012661= | G368: ='Pagina de sistema'!C354 | H368: ='Pagina de sistema'!B354
A369: SOMENTE CLICAR -> | C369: ='Pagina de sistema'!F355 -> https://docs.google.com/forms/d/e/1FAIpQLSdL6XnoqNKTAw7dlsIr2ZZmRPtlLw-idLKWanRUaG1h56cebg/viewform?entry.1095270279=&entry.191341224=&entry.2101494904=Dúvida&entry.1095270279=&entry.950207260=&entry.237710686=&entry.1585267062=&entry.409012661= | G369: ='Pagina de sistema'!C355 | H369: ='Pagina de sistema'!B355 | Y369: BRUNO ARRUDA SANTOS | Z369: REGIANE APARECIDA DA SILVA | AA369: 4509363 | AB369: 14:20:00 | AC369: WILSON ALBERTO TROCOLI CONCEICAO | AD369: OSASCO | AE369: LATAM - LAE - PI CASOS | AF369: BRUNO ARRUDA SANTOS
A370: SOMENTE CLICAR -> | C370: ='Pagina de sistema'!F356 -> https://docs.google.com/forms/d/e/1FAIpQLSdL6XnoqNKTAw7dlsIr2ZZmRPtlLw-idLKWanRUaG1h56cebg/viewform?entry.1095270279=&entry.191341224=&entry.2101494904=Dúvida&entry.1095270279=&entry.950207260=&entry.237710686=&entry.1585267062=&entry.409012661= | G370: ='Pagina de sistema'!C356 | H370: ='Pagina de sistema'!B356 | Y370: GLYCIA LUDUVICE BARBOZA | Z370: RAFAEL DA SILVA ALVES | AA370: 4509383 | AB370: 07:40:00 | AC370: WILSON ALBERTO TROCOLI CONCEICAO | AD370: OSASCO | AE370: LATAM - CORPORATE - AGENCIA E-MAIL | AF370: GLYCIA LUDUVICE BARBOZA
A371: SOMENTE CLICAR -> | C371: ='Pagina de sistema'!F357 -> https://docs.google.com/forms/d/e/1FAIpQLSdL6XnoqNKTAw7dlsIr2ZZmRPtlLw-idLKWanRUaG1h56cebg/viewform?entry.1095270279=&entry.191341224=&entry.2101494904=Dúvida&entry.1095270279=&entry.950207260=&entry.237710686=&entry.1585267062=&entry.409012661= | G371: ='Pagina de sistema'!C357 | H371: ='Pagina de sistema'!B357 | Y371: SAMILA SAMPAIO DOS SANTOS NASCIMENTO | Z371: FERNANDO BRITO BORGES | AA371: 4509388 | AB371: 08:00:00 | AC371: RENATA SIMARA FERREIRA | AD371: OSASCO | AE371: LATAM - LUA - TRAVEL VOZ | AF371: SAMILA SAMPAIO DOS SANTOS NASCIMENTO
A372: SOMENTE CLICAR -> | C372: ='Pagina de sistema'!F358 -> https://docs.google.com/forms/d/e/1FAIpQLSdL6XnoqNKTAw7dlsIr2ZZmRPtlLw-idLKWanRUaG1h56cebg/viewform?entry.1095270279=&entry.191341224=&entry.2101494904=Dúvida&entry.1095270279=&entry.950207260=&entry.237710686=&entry.1585267062=&entry.409012661= | G372: ='Pagina de sistema'!C358 | H372: ='Pagina de sistema'!B358 | Y372: SILVIA LETICIA SOUSA SANTOS | Z372: KATLYN LOWYSE KUCHTA DE ALMEIDA PINTO | AA372: 4509390 | AB372: 08:00:00 | AC372: WILSON ALBERTO TROCOLI CONCEICAO | AD372: OSASCO | AE372: LATAM - LAE - CONCILIAÇÃO CHAT | AF372: SILVIA LETICIA SOUSA SANTOS
A373: SOMENTE CLICAR -> | C373: ='Pagina de sistema'!F359 -> https://docs.google.com/forms/d/e/1FAIpQLSdL6XnoqNKTAw7dlsIr2ZZmRPtlLw-idLKWanRUaG1h56cebg/viewform?entry.1095270279=&entry.191341224=&entry.2101494904=Dúvida&entry.1095270279=&entry.950207260=&entry.237710686=&entry.1585267062=&entry.409012661= | G373: ='Pagina de sistema'!C359 | H373: ='Pagina de sistema'!B359 | Y373: ELENILDE DOS SANTOS SOUZA | Z373: JEFFERSON SILVA RIBEIRO | AA373: 4509405 | AB373: 08:00:00 | AC373: WILSON ALBERTO TROCOLI CONCEICAO | AD373: OSASCO | AE373: LATAM - CARGO - CUSTOMER CARE BKO | AF373: ELENILDE DOS SANTOS SOUZA
A374: SOMENTE CLICAR -> | C374: ='Pagina de sistema'!F360 -> https://docs.google.com/forms/d/e/1FAIpQLSdL6XnoqNKTAw7dlsIr2ZZmRPtlLw-idLKWanRUaG1h56cebg/viewform?entry.1095270279=&entry.191341224=&entry.2101494904=Dúvida&entry.1095270279=&entry.950207260=&entry.237710686=&entry.1585267062=&entry.409012661= | G374: ='Pagina de sistema'!C360 | H374: ='Pagina de sistema'!B360 | Y374: LETHICIA SOUSA FEITOSA | Z374: JOAO KEVIN DE LIMA BEZERRA | AA374: 4509423 | AB374: 07:00:00 | AC374: WILSON ALBERTO TROCOLI CONCEICAO | AD374: OSASCO | AE374: LATAM - DREAM TEAM - REEMBOLSO CASOS | AF374: LETHICIA SOUSA FEITOSA
A375: SOMENTE CLICAR -> | C375: ='Pagina de sistema'!F361 -> https://docs.google.com/forms/d/e/1FAIpQLSdL6XnoqNKTAw7dlsIr2ZZmRPtlLw-idLKWanRUaG1h56cebg/viewform?entry.1095270279=&entry.191341224=&entry.2101494904=Dúvida&entry.1095270279=&entry.950207260=&entry.237710686=&entry.1585267062=&entry.409012661= | G375: ='Pagina de sistema'!C361 | H375: ='Pagina de sistema'!B361 | Y375: FABIANA CRISTINA FERREIRA | Z375: JOAO KEVIN DE LIMA BEZERRA | AA375: 4509428 | AB375: 06:00:00 | AC375: WILSON ALBERTO TROCOLI CONCEICAO | AD375: OSASCO | AE375: LATAM - DREAM TEAM - REEMBOLSO CASOS | AF375: FABIANA CRISTINA FERREIRA
A376: SOMENTE CLICAR -> | C376: ='Pagina de sistema'!F362 -> https://docs.google.com/forms/d/e/1FAIpQLSdL6XnoqNKTAw7dlsIr2ZZmRPtlLw-idLKWanRUaG1h56cebg/viewform?entry.1095270279=&entry.191341224=&entry.2101494904=Dúvida&entry.1095270279=&entry.950207260=&entry.237710686=&entry.1585267062=&entry.409012661= | G376: ='Pagina de sistema'!C362 | H376: ='Pagina de sistema'!B362 | Y376: LUANA MONTENEGRO SANTOS | Z376: CASSYA YONA VILLELA | AA376: 4509446 | AB376: 07:00:00 | AC376: - | AD376: LIBERO | AE376: LATAM - SUPORTE - FIELD SUPORT CHAT | AF376: LUANA MONTENEGRO SANTOS
A377: SOMENTE CLICAR -> | C377: ='Pagina de sistema'!F363 -> https://docs.google.com/forms/d/e/1FAIpQLSdL6XnoqNKTAw7dlsIr2ZZmRPtlLw-idLKWanRUaG1h56cebg/viewform?entry.1095270279=&entry.191341224=&entry.2101494904=Dúvida&entry.1095270279=&entry.950207260=&entry.237710686=&entry.1585267062=&entry.409012661= | G377: ='Pagina de sistema'!C363 | H377: ='Pagina de sistema'!B363 | Y377: JADIEL DE SOUSA FERREIRA | Z377: HERMES RODRIGUES DA SILVA | AA377: 4510607 | AB377: 23:20:00 | AC377: RENATA SIMARA FERREIRA | AD377: OSASCO | AE377: LATAM - SUPORTE - VOZ | AF377: JADIEL DE SOUSA FERREIRA
A378: SOMENTE CLICAR -> | C378: ='Pagina de sistema'!F364 -> https://docs.google.com/forms/d/e/1FAIpQLSdL6XnoqNKTAw7dlsIr2ZZmRPtlLw-idLKWanRUaG1h56cebg/viewform?entry.1095270279=&entry.191341224=&entry.2101494904=Dúvida&entry.1095270279=&entry.950207260=&entry.237710686=&entry.1585267062=&entry.409012661= | G378: ='Pagina de sistema'!C364 | H378: ='Pagina de sistema'!B364 | Y378: KELLY JESUS DA SILVA | Z378: MONICA VALIM RAMOS | AA378: 4510623 | AB378: 09:00:00 | AC378: WILSON ALBERTO TROCOLI CONCEICAO | AD378: OSASCO | AE378: LATAM - LAE - PI CASOS | AF378: KELLY JESUS DA SILVA
A379: SOMENTE CLICAR -> | C379: ='Pagina de sistema'!F365 -> https://docs.google.com/forms/d/e/1FAIpQLSdL6XnoqNKTAw7dlsIr2ZZmRPtlLw-idLKWanRUaG1h56cebg/viewform?entry.1095270279=&entry.191341224=&entry.2101494904=Dúvida&entry.1095270279=&entry.950207260=&entry.237710686=&entry.1585267062=&entry.409012661= | G379: ='Pagina de sistema'!C365 | H379: ='Pagina de sistema'!B365 | Y379: LARISSA BARBOSA DE OLIVEIRA | Z379: JOAO KEVIN DE LIMA BEZERRA | AA379: 4510624 | AB379: 08:00:00 | AC379: WILSON ALBERTO TROCOLI CONCEICAO | AD379: OSASCO | AE379: LATAM - DREAM TEAM - REEMBOLSO VOZ | AF379: LARISSA BARBOSA DE OLIVEIRA
A380: SOMENTE CLICAR -> | C380: ='Pagina de sistema'!F366 -> https://docs.google.com/forms/d/e/1FAIpQLSdL6XnoqNKTAw7dlsIr2ZZmRPtlLw-idLKWanRUaG1h56cebg/viewform?entry.1095270279=&entry.191341224=&entry.2101494904=Dúvida&entry.1095270279=&entry.950207260=&entry.237710686=&entry.1585267062=&entry.409012661= | G380: ='Pagina de sistema'!C366 | H380: ='Pagina de sistema'!B366 | Y380: APARECIDA CRISTINA DE OLIVEIRA | Z380: FERNANDO BRITO BORGES | AA380: 4510689 | AB380: 08:00:00 | AC380: RENATA SIMARA FERREIRA | AD380: OSASCO | AE380: LATAM - LUA VOZ | AF380: APARECIDA CRISTINA DE OLIVEIRA
... A1001: SOMENTE CLICAR -> | C1001: ='Pagina de sistema'!F987 -> https://docs.google.com/forms/d/e/1FAIpQLSdL6XnoqNKTAw7dlsIr2ZZmRPtlLw-idLKWanRUaG1h56cebg/viewform?entry.1095270279=&entry.191341224=&entry.2101494904=Dúvida&entry.1095270279=&entry.950207260=&entry.237710686=&entry.1585267062=&entry.409012661= | G1001: ='Pagina de sistema'!C987 | H1001: ='Pagina de sistema'!B987 | Y1001: VITORIA KAROLINA IZIDIO | Z1001: JULIANA DANTAS DOS SANTOS | AA1001: 4714942 | AB1001: 06:30:00 | AC1001: RENATA SIMARA FERREIRA | AD1001: OSASCO | AE1001: LATAM - LUA CHAT/WHATS | AF1001: VITORIA KAROLINA IZIDIO
Y1002: MAURICIO DOS SANTOS AGUIAR | Z1002: DERIVAL MANOEL DE OLIVEIRA | AA1002: 4715003 | AB1002: 15:50:00 | AC1002: - | AD1002: LIBERO | AE1002: LATAM - HVC BLACK VOZ | AF1002: MAURICIO DOS SANTOS AGUIAR
Y1003: REBECCA VITORIA DOS SANTOS BARBOSA | Z1003: CAIO HENRIQUE FERRARACIO DA FONSECA | AA1003: 4715053 | AB1003: 14:50:00 | AC1003: RENATA SIMARA FERREIRA | AD1003: 7 DE ABRIL | AE1003: LATAM - SUPORTE - VOZ | AF1003: REBECCA VITORIA DOS SANTOS BARBOSA
Y1004: DANIEL PHILIPE FRANCOIS RAMOS | Z1004: BRUNA DE LIMA BARBOZA | AA1004: 4715116 | AB1004: 23:20:00 | AC1004: WILSON ALBERTO TROCOLI CONCEICAO | AD1004: OSASCO | AE1004: LATAM - DREAM TEAM - BAGAGENS VOZ | AF1004: DANIEL PHILIPE FRANCOIS RAMOS
Y1005: KALLEL OLIVEIRA VILEMAR | Z1005: BRUNA DE LIMA BARBOZA | AA1005: 4715121 | AB1005: 23:20:00 | AC1005: WILSON ALBERTO TROCOLI CONCEICAO | AD1005: OSASCO | AE1005: LATAM - DREAM TEAM - BAGAGENS VOZ | AF1005: KALLEL OLIVEIRA VILEMAR
Y1006: MICHELE DI LALLO NETO | Z1006: JOAO KEVIN DE LIMA BEZERRA | AA1006: 4715123 | AB1006: 17:00:00 | AC1006: WILSON ALBERTO TROCOLI CONCEICAO | AD1006: OSASCO | AE1006: LATAM - DREAM TEAM - REEMBOLSO VOZ | AF1006: MICHELE DI LALLO NETO
Y1007: MARCELLO CLEMENTE MAKHAJDA | Z1007: BRUNA DE LIMA BARBOZA | AA1007: 4715131 | AB1007: 17:00:00 | AC1007: WILSON ALBERTO TROCOLI CONCEICAO | AD1007: OSASCO | AE1007: LATAM - DREAM TEAM - BAGAGENS WHATS | AF1007: MARCELLO CLEMENTE MAKHAJDA
Y1008: MELISSA GRACIELY DOURADO DAMASCENO | Z1008: GUSTAVO DA SILVA MARTINES DAMICO | AA1008: 4721632 | AB1008: 19:20:00 | AC1008: - | AD1008: HOME SP | AE1008: LATAM - HVC BLACK VOZ | AF1008: MELISSA GRACIELY DOURADO DAMASCENO
Y1009: RAIANE LUCIANA ODORICO DE JESUS | Z1009: MILLENY SOUZA NUNES | AA1009: 4721637 | AB1009: 05:40:00 | AC1009: WILSON ALBERTO TROCOLI CONCEICAO | AD1009: 7 DE ABRIL | AE1009: LATAM - DREAM TEAM - FFP VOZ | AF1009: RAIANE LUCIANA ODORICO DE JESUS
Y1010: WENDELL HENRIQUE RODRIGUES SANTANA LIMA | Z1010: GUSTAVO DA SILVA MARTINES DAMICO | AA1010: 4721651 | AB1010: 15:50:00 | AC1010: - | AD1010: LIBERO | AE1010: LATAM - HVC BLACK VOZ | AF1010: WENDELL HENRIQUE RODRIGUES SANTANA LIMA
Y1011: MICHEL TIAGO DE SANTANA | Z1011: GUSTAVO DA SILVA MARTINES DAMICO | AA1011: 4721676 | AB1011: 15:20:00 | AC1011: - | AD1011: LIBERO | AE1011: LATAM - HVC BLACK VOZ | AF1011: MICHEL TIAGO DE SANTANA
Y1012: DENISE DA SILVA | Z1012: GUSTAVO DA SILVA MARTINES DAMICO | AA1012: 4721699 | AB1012: 17:10:00 | AC1012: - | AD1012: LIBERO | AE1012: LATAM - HVC BLACK VOZ | AF1012: DENISE DA SILVA
Y1013: WILLIAM MEDEIROS OKA | Z1013: GUSTAVO DA SILVA MARTINES DAMICO | AA1013: 4721705 | AB1013: 19:20:00 | AC1013: - | AD1013: HOME SP | AE1013: LATAM - HVC BLACK VOZ | AF1013: WILLIAM MEDEIROS OKA
... Y2150: RAFAELA AVILA DA CRUZ | Z2150: - | AA2150: 4818817 | AB2150: 16:20:00 | AC2150: - | AD2150: SALVADOR | AE2150: DEPOSITO DE NOVOS | AF2150: RAFAELA AVILA DA CRUZ

Sheet Pagina de sistema
A1: BP AGENTE | B1: NOME AGENTE | C1: PNR | D1: MOTIVO CALL | E1: NOTA AGENTE | F1: COPIAR LINK E COLAR NO NAVEGADOR | G1: :) | H1: COMENTÁRIO ADICIONAL: (aparece no forms tbm) | K1: CAIXA DE MOTIVOS NO FORMULÁRIO DE TIPICAÇÃO | N1: Construção total | O1: Construção: | Q1: SISTEMA: | R1: LINK | S1: LÓGICA GRUPO | T1: LÓGICA AVALIAÇÃO BOM | U1: LÓGICA AVALIAÇÃO MEDIANO | V1: LÓGICA AVALIAÇÃO RUIM | W1: LÓGICA DE COMENTÁRIO
F2: =N2 -> https://docs.google.com/forms/d/e/1FAIpQLSdL6XnoqNKTAw7dlsIr2ZZmRPtlLw-idLKWanRUaG1h56cebg/viewform?entry.1095270279=&entry.191341224=&entry.2101494904=Dúvida&entry.1095270279=&entry.950207260=&entry.237710686=&entry.1585267062=&entry.409012661= | G2: <-- clica copie e cole lá no navegador | K2: Bilhetes com Remark de Autorização para Casos Médicos, de acordo com a política anterior ao E-Business | N2: =$R$2&O2 -> https://docs.google.com/forms/d/e/1FAIpQLSdL6XnoqNKTAw7dlsIr2ZZmRPtlLw-idLKWanRUaG1h56cebg/viewform?entry.1095270279=&entry.191341224=&entry.2101494904=Dúvida&entry.1095270279=&entry.950207260=&entry.237710686=&entry.1585267062=&entry.409012661= | O2: =$Q$2&A2&$Q$3&C2&$Q$4&$S2&$Q$2&$Q$5&D2&$Q$6&D2&$T2&$U2&$V2&W2 -> entry.1095270279=&entry.191341224=&entry.2101494904=Dúvida&entry.1095270279=&entry.950207260=&entry.237710686=&entry.1585267062=&entry.409012661= | P2: BP AGENTE | Q2: entry.1095270279= | R2: https://docs.google.com/forms/d/e/1FAIpQLSdL6XnoqNKTAw7dlsIr2ZZmRPtlLw-idLKWanRUaG1h56cebg/viewform? | S2: =IF(COUNTIF($K$2:$K$21,D2)>0,"Execução&","Dúvida&") -> Dúvida& | T2: =IF(E2="BOM","&entry.2006968231=O agente demonstra conhecer o processo, mas aciona para validar a informação.","") | U2: =IF(E2="MEDIANO","&entry.2006968231=O agente demonstra não saber como conduzir a situação com o cliente&entry.2006968231=Falta de conhecimento da ferramenta","") | V2: =IF(E2="RUIM","&entry.2006968231=O agente demonstra não saber como conduzir a situação com o cliente&entry.2006968231=Falta de conhecimento da ferramenta&entry.2006968231=Não ter realizado a leitura no PIC ou CDA (Central de Ajuda Site Latam)&entry.2006968231=Não saber "&"interpretar a informação no PIC ou CDA (Central de Ajuda Site Latam)","") | W2: =$Z$2&H2&$Y$2&H2 -> &entry.1585267062=&entry.409012661= | X2: :) | Y2: &entry.409012661= | Z2: &entry.1585267062=
F3: =N3 -> https://docs.google.com/forms/d/e/1FAIpQLSdL6XnoqNKTAw7dlsIr2ZZmRPtlLw-idLKWanRUaG1h56cebg/viewform?entry.1095270279=&entry.191341224=&entry.2101494904=Dúvida&entry.1095270279=&entry.950207260=&entry.237710686=&entry.1585267062=&entry.409012661= | G3: <-- clica copie e cole lá no navegador | K3: Cabine Discordante | N3: =$R$2&O3 -> https://docs.google.com/forms/d/e/1FAIpQLSdL6XnoqNKTAw7dlsIr2ZZmRPtlLw-idLKWanRUaG1h56cebg/viewform?entry.1095270279=&entry.191341224=&entry.2101494904=Dúvida&entry.1095270279=&entry.950207260=&entry.237710686=&entry.1585267062=&entry.409012661= | O3: =$Q$2&A3&$Q$3&C3&$Q$4&$S3&$Q$2&$Q$5&D3&$Q$6&D3&$T3&$U3&$V3&W3 -> entry.1095270279=&entry.191341224=&entry.2101494904=Dúvida&entry.1095270279=&entry.950207260=&entry.237710686=&entry.1585267062=&entry.409012661= | P3: PNR OU ORDEM DE BILHETE | Q3: &entry.191341224= | S3: =IF(COUNTIF($K$2:$K$21,D3)>0,"Execução&","Dúvida&") -> Dúvida& | T3: =IF(E3="BOM","&entry.2006968231=O agente demonstra conhecer o processo, mas aciona para validar a informação.","") | U3: =IF(E3="MEDIANO","&entry.2006968231=O agente demonstra não saber como conduzir a situação com o cliente&entry.2006968231=Falta de conhecimento da ferramenta","") | V3: =IF(E3="RUIM","&entry.2006968231=O agente demonstra não saber como conduzir a situação com o cliente&entry.2006968231=Falta de conhecimento da ferramenta&entry.2006968231=Não ter realizado a leitura no PIC ou CDA (Central de Ajuda Site Latam)&entry.2006968231=Não saber "&"interpretar a informação no PIC ou CDA (Central de Ajuda Site Latam)","") | W3: =$Z$2&H3&$Y$2&H3 -> &entry.1585267062=&entry.409012661=
F4: =N4 -> https://docs.google.com/forms/d/e/1FAIpQLSdL6XnoqNKTAw7dlsIr2ZZmRPtlLw-idLKWanRUaG1h56cebg/viewform?entry.1095270279=&entry.191341224=&entry.2101494904=Dúvida&entry.1095270279=&entry.950207260=&entry.237710686=&entry.1585267062=&entry.409012661= | G4: <-- clica copie e cole lá no navegador | K4: Correção de Nome ou Sobrenome | N4: =$R$2&O4 -> https://docs.google.com/forms/d/e/1FAIpQLSdL6XnoqNKTAw7dlsIr2ZZmRPtlLw-idLKWanRUaG1h56cebg/viewform?entry.1095270279=&entry.191341224=&entry.2101494904=Dúvida&entry.1095270279=&entry.950207260=&entry.237710686=&entry.1585267062=&entry.409012661= | O4: =$Q$2&A4&$Q$3&C4&$Q$4&$S4&$Q$2&$Q$5&D4&$Q$6&D4&$T4&$U4&$V4&W4 -> entry.1095270279=&entry.191341224=&entry.2101494904=Dúvida&entry.1095270279=&entry.950207260=&entry.237710686=&entry.1585267062=&entry.409012661= | P4: MOTIVO DA LIGAÇÃO | Q4: &entry.2101494904= | S4: =IF(COUNTIF($K$2:$K$21,D4)>0,"Execução&","Dúvida&") -> Dúvida& | T4: =IF(E4="BOM","&entry.2006968231=O agente demonstra conhecer o processo, mas aciona para validar a informação.","") | U4: =IF(E4="MEDIANO","&entry.2006968231=O agente demonstra não saber como conduzir a situação com o cliente&entry.2006968231=Falta de conhecimento da ferramenta","") | V4: =IF(E4="RUIM","&entry.2006968231=O agente demonstra não saber como conduzir a situação com o cliente&entry.2006968231=Falta de conhecimento da ferramenta&entry.2006968231=Não ter realizado a leitura no PIC ou CDA (Central de Ajuda Site Latam)&entry.2006968231=Não saber "&"interpretar a informação no PIC ou CDA (Central de Ajuda Site Latam)","") | W4: =$Z$2&H4&$Y$2&H4 -> &entry.1585267062=&entry.409012661=
F5: =N5 -> https://docs.google.com/forms/d/e/1FAIpQLSdL6XnoqNKTAw7dlsIr2ZZmRPtlLw-idLKWanRUaG1h56cebg/viewform?entry.1095270279=&entry.191341224=&entry.2101494904=Dúvida&entry.1095270279=&entry.950207260=&entry.237710686=&entry.1585267062=&entry.409012661= | G5: <-- clica copie e cole lá no navegador | K5: Emissão com documentos comprobatórios | N5: =$R$2&O5 -> https://docs.google.com/forms/d/e/1FAIpQLSdL6XnoqNKTAw7dlsIr2ZZmRPtlLw-idLKWanRUaG1h56cebg/viewform?entry.1095270279=&entry.191341224=&entry.2101494904=Dúvida&entry.1095270279=&entry.950207260=&entry.237710686=&entry.1585267062=&entry.409012661= | O5: =$Q$2&A5&$Q$3&C5&$Q$4&$S5&$Q$2&$Q$5&D5&$Q$6&D5&$T5&$U5&$V5&W5 -> entry.1095270279=&entry.191341224=&entry.2101494904=Dúvida&entry.1095270279=&entry.950207260=&entry.237710686=&entry.1585267062=&entry.409012661= | P5: PROCESSOS REALIZADOS | Q5: &entry.950207260= | S5: =IF(COUNTIF($K$2:$K$21,D5)>0,"Execução&","Dúvida&") -> Dúvida& | T5: =IF(E5="BOM","&entry.2006968231=O agente demonstra conhecer o processo, mas aciona para validar a informação.","") | U5: =IF(E5="MEDIANO","&entry.2006968231=O agente demonstra não saber como conduzir a situação com o cliente&entry.2006968231=Falta de conhecimento da ferramenta","") | V5: =IF(E5="RUIM","&entry.2006968231=O agente demonstra não saber como conduzir a situação com o cliente&entry.2006968231=Falta de conhecimento da ferramenta&entry.2006968231=Não ter realizado a leitura no PIC ou CDA (Central de Ajuda Site Latam)&entry.2006968231=Não saber "&"interpretar a informação no PIC ou CDA (Central de Ajuda Site Latam)","") | W5: =$Z$2&H5&$Y$2&H5 -> &entry.1585267062=&entry.409012661=
F6: =N6 -> https://docs.google.com/forms/d/e/1FAIpQLSdL6XnoqNKTAw7dlsIr2ZZmRPtlLw-idLKWanRUaG1h56cebg/viewform?entry.1095270279=&entry.191341224=&entry.2101494904=Dúvida&entry.1095270279=&entry.950207260=&entry.237710686=&entry.1585267062=&entry.409012661= | G6: <-- clica copie e cole lá no navegador | K6: Emissão de tickets sem um código de imposto | N6: =$R$2&O6 -> https://docs.google.com/forms/d/e/1FAIpQLSdL6XnoqNKTAw7dlsIr2ZZmRPtlLw-idLKWanRUaG1h56cebg/viewform?entry.1095270279=&entry.191341224=&entry.2101494904=Dúvida&entry.1095270279=&entry.950207260=&entry.237710686=&entry.1585267062=&entry.409012661= | O6: =$Q$2&A6&$Q$3&C6&$Q$4&$S6&$Q$2&$Q$5&D6&$Q$6&D6&$T6&$U6&$V6&W6 -> entry.1095270279=&entry.191341224=&entry.2101494904=Dúvida&entry.1095270279=&entry.950207260=&entry.237710686=&entry.1585267062=&entry.409012661= | P6: QUAIS DÚVIDAS FORAM ABORDADAS | Q6: &entry.237710686= | S6: =IF(COUNTIF($K$2:$K$21,D6)>0,"Execução&","Dúvida&") -> Dúvida& | T6: =IF(E6="BOM","&entry.2006968231=O agente demonstra conhecer o processo, mas aciona para validar a informação.","") | U6: =IF(E6="MEDIANO","&entry.2006968231=O agente demonstra não saber como conduzir a situação com o cliente&entry.2006968231=Falta de conhecimento da ferramenta","") | V6: =IF(E6="RUIM","&entry.2006968231=O agente demonstra não saber como conduzir a situação com o cliente&entry.2006968231=Falta de conhecimento da ferramenta&entry.2006968231=Não ter realizado a leitura no PIC ou CDA (Central de Ajuda Site Latam)&entry.2006968231=Não saber "&"interpretar a informação no PIC ou CDA (Central de Ajuda Site Latam)","") | W6: =$Z$2&H6&$Y$2&H6 -> &entry.1585267062=&entry.409012661=
F7: =N7 -> https://docs.google.com/forms/d/e/1FAIpQLSdL6XnoqNKTAw7dlsIr2ZZmRPtlLw-idLKWanRUaG1h56cebg/viewform?entry.1095270279=&entry.191341224=&entry.2101494904=Dúvida&entry.1095270279=&entry.950207260=&entry.237710686=&entry.1585267062=&entry.409012661= | G7: <-- clica copie e cole lá no navegador | K7: EXST/CBBG (Emissão) | N7: =$R$2&O7 -> https://docs.google.com/forms/d/e/1FAIpQLSdL6XnoqNKTAw7dlsIr2ZZmRPtlLw-idLKWanRUaG1h56cebg/viewform?entry.1095270279=&entry.191341224=&entry.2101494904=Dúvida&entry.1095270279=&entry.950207260=&entry.237710686=&entry.1585267062=&entry.409012661= | O7: =$Q$2&A7&$Q$3&C7&$Q$4&$S7&$Q$2&$Q$5&D7&$Q$6&D7&$T7&$U7&$V7&W7 -> entry.1095270279=&entry.191341224=&entry.2101494904=Dúvida&entry.1095270279=&entry.950207260=&entry.237710686=&entry.1585267062=&entry.409012661= | P7: Salvar e-mail google | Q7: &emailReceipt=true | S7: =IF(COUNTIF($K$2:$K$21,D7)>0,"Execução&","Dúvida&") -> Dúvida& | T7: =IF(E7="BOM","&entry.2006968231=O agente demonstra conhecer o processo, mas aciona para validar a informação.","") | U7: =IF(E7="MEDIANO","&entry.2006968231=O agente demonstra não saber como conduzir a situação com o cliente&entry.2006968231=Falta de conhecimento da ferramenta","") | V7: =IF(E7="RUIM","&entry.2006968231=O agente demonstra não saber como conduzir a situação com o cliente&entry.2006968231=Falta de conhecimento da ferramenta&entry.2006968231=Não ter realizado a leitura no PIC ou CDA (Central de Ajuda Site Latam)&entry.2006968231=Não saber "&"interpretar a informação no PIC ou CDA (Central de Ajuda Site Latam)","") | W7: =$Z$2&H7&$Y$2&H7 -> &entry.1585267062=&entry.409012661=
F8: =N8 -> https://docs.google.com/forms/d/e/1FAIpQLSdL6XnoqNKTAw7dlsIr2ZZmRPtlLw-idLKWanRUaG1h56cebg/viewform?entry.1095270279=&entry.191341224=&entry.2101494904=Dúvida&entry.1095270279=&entry.950207260=&entry.237710686=&entry.1585267062=&entry.409012661= | G8: <-- clica copie e cole lá no navegador | K8: EXST/CBBG (Adicionar serviço em uma reserva já emitida) | N8: =$R$2&O8 -> https://docs.google.com/forms/d/e/1FAIpQLSdL6XnoqNKTAw7dlsIr2ZZmRPtlLw-idLKWanRUaG1h56cebg/viewform?entry.1095270279=&entry.191341224=&entry.2101494904=Dúvida&entry.1095270279=&entry.950207260=&entry.237710686=&entry.1585267062=&entry.409012661= | O8: =$Q$2&A8&$Q$3&C8&$Q$4&$S8&$Q$2&$Q$5&D8&$Q$6&D8&$T8&$U8&$V8&W8 -> entry.1095270279=&entry.191341224=&entry.2101494904=Dúvida&entry.1095270279=&entry.950207260=&entry.237710686=&entry.1585267062=&entry.409012661= | S8: =IF(COUNTIF($K$2:$K$21,D8)>0,"Execução&","Dúvida&") -> Dúvida& | T8: =IF(E8="BOM","&entry.2006968231=O agente demonstra conhecer o processo, mas aciona para validar a informação.","") | U8: =IF(E8="MEDIANO","&entry.2006968231=O agente demonstra não saber como conduzir a situação com o cliente&entry.2006968231=Falta de conhecimento da ferramenta","") | V8: =IF(E8="RUIM","&entry.2006968231=O agente demonstra não saber como conduzir a situação com o cliente&entry.2006968231=Falta de conhecimento da ferramenta&entry.2006968231=Não ter realizado a leitura no PIC ou CDA (Central de Ajuda Site Latam)&entry.2006968231=Não saber "&"interpretar a informação no PIC ou CDA (Central de Ajuda Site Latam)","") | W8: =$Z$2&H8&$Y$2&H8 -> &entry.1585267062=&entry.409012661=
F9: =N9 -> https://docs.google.com/forms/d/e/1FAIpQLSdL6XnoqNKTAw7dlsIr2ZZmRPtlLw-idLKWanRUaG1h56cebg/viewform?entry.1095270279=&entry.191341224=&entry.2101494904=Dúvida&entry.1095270279=&entry.950207260=&entry.237710686=&entry.1585267062=&entry.409012661= | G9: <-- clica copie e cole lá no navegador | K9: EXST/CBBG (Remarcação) | N9: =$R$2&O9 -> https://docs.google.com/forms/d/e/1FAIpQLSdL6XnoqNKTAw7dlsIr2ZZmRPtlLw-idLKWanRUaG1h56cebg/viewform?entry.1095270279=&entry.191341224=&entry.2101494904=Dúvida&entry.1095270279=&entry.950207260=&entry.237710686=&entry.1585267062=&entry.409012661= | O9: =$Q$2&A9&$Q$3&C9&$Q$4&$S9&$Q$2&$Q$5&D9&$Q$6&D9&$T9&$U9&$V9&W9 -> entry.1095270279=&entry.191341224=&entry.2101494904=Dúvida&entry.1095270279=&entry.950207260=&entry.237710686=&entry.1585267062=&entry.409012661= | S9: =IF(COUNTIF($K$2:$K$21,D9)>0,"Execução&","Dúvida&") -> Dúvida& | T9: =IF(E9="BOM","&entry.2006968231=O agente demonstra conhecer o processo, mas aciona para validar a informação.","") | U9: =IF(E9="MEDIANO","&entry.2006968231=O agente demonstra não saber como conduzir a situação com o cliente&entry.2006968231=Falta de conhecimento da ferramenta","") | V9: =IF(E9="RUIM","&entry.2006968231=O agente demonstra não saber como conduzir a situação com o cliente&entry.2006968231=Falta de conhecimento da ferramenta&entry.2006968231=Não ter realizado a leitura no PIC ou CDA (Central de Ajuda Site Latam)&entry.2006968231=Não saber "&"interpretar a informação no PIC ou CDA (Central de Ajuda Site Latam)","") | W9: =$Z$2&H9&$Y$2&H9 -> &entry.1585267062=&entry.409012661=
F10: =N10 -> https://docs.google.com/forms/d/e/1FAIpQLSdL6XnoqNKTAw7dlsIr2ZZmRPtlLw-idLKWanRUaG1h56cebg/viewform?entry.1095270279=&entry.191341224=&entry.2101494904=Dúvida&entry.1095270279=&entry.950207260=&entry.237710686=&entry.1585267062=&entry.409012661= | G10: <-- clica copie e cole lá no navegador | K10: Honrar tarifa BR | N10: =$R$2&O10 -> https://docs.google.com/forms/d/e/1FAIpQLSdL6XnoqNKTAw7dlsIr2ZZmRPtlLw-idLKWanRUaG1h56cebg/viewform?entry.1095270279=&entry.191341224=&entry.2101494904=Dúvida&entry.1095270279=&entry.950207260=&entry.237710686=&entry.1585267062=&entry.409012661= | O10: =$Q$2&A10&$Q$3&C10&$Q$4&$S10&$Q$2&$Q$5&D10&$Q$6&D10&$T10&$U10&$V10&W10 -> entry.1095270279=&entry.191341224=&entry.2101494904=Dúvida&entry.1095270279=&entry.950207260=&entry.237710686=&entry.1585267062=&entry.409012661= | S10: =IF(COUNTIF($K$2:$K$21,D10)>0,"Execução&","Dúvida&") -> Dúvida& | T10: =IF(E10="BOM","&entry.2006968231=O agente demonstra conhecer o processo, mas aciona para validar a informação.","") | U10: =IF(E10="MEDIANO","&entry.2006968231=O agente demonstra não saber como conduzir a situação com o cliente&entry.2006968231=Falta de conhecimento da ferramenta","") | V10: =IF(E10="RUIM","&entry.2006968231=O agente demonstra não saber como conduzir a situação com o cliente&entry.2006968231=Falta de conhecimento da ferramenta&entry.2006968231=Não ter realizado a leitura no PIC ou CDA (Central de Ajuda Site Latam)&entry.2006968231=Não saber "&"interpretar a informação no PIC ou CDA (Central de Ajuda Site Latam)","") | W10: =$Z$2&H10&$Y$2&H10 -> &entry.1585267062=&entry.409012661=
F11: =N11 -> https://docs.google.com/forms/d/e/1FAIpQLSdL6XnoqNKTAw7dlsIr2ZZmRPtlLw-idLKWanRUaG1h56cebg/viewform?entry.1095270279=&entry.191341224=&entry.2101494904=Dúvida&entry.1095270279=&entry.950207260=&entry.237710686=&entry.1585267062=&entry.409012661= | G11: <-- clica copie e cole lá no navegador | K11: Ingresso de POC através Interact | N11: =$R$2&O11 -> https://docs.google.com/forms/d/e/1FAIpQLSdL6XnoqNKTAw7dlsIr2ZZmRPtlLw-idLKWanRUaG1h56cebg/viewform?entry.1095270279=&entry.191341224=&entry.2101494904=Dúvida&entry.1095270279=&entry.950207260=&entry.237710686=&entry.1585267062=&entry.409012661= | O11: =$Q$2&A11&$Q$3&C11&$Q$4&$S11&$Q$2&$Q$5&D11&$Q$6&D11&$T11&$U11&$V11&W11 -> entry.1095270279=&entry.191341224=&entry.2101494904=Dúvida&entry.1095270279=&entry.950207260=&entry.237710686=&entry.1585267062=&entry.409012661= | S11: =IF(COUNTIF($K$2:$K$21,D11)>0,"Execução&","Dúvida&") -> Dúvida& | T11: =IF(E11="BOM","&entry.2006968231=O agente demonstra conhecer o processo, mas aciona para validar a informação.","") | U11: =IF(E11="MEDIANO","&entry.2006968231=O agente demonstra não saber como conduzir a situação com o cliente&entry.2006968231=Falta de conhecimento da ferramenta","") | V11: =IF(E11="RUIM","&entry.2006968231=O agente demonstra não saber como conduzir a situação com o cliente&entry.2006968231=Falta de conhecimento da ferramenta&entry.2006968231=Não ter realizado a leitura no PIC ou CDA (Central de Ajuda Site Latam)&entry.2006968231=Não saber "&"interpretar a informação no PIC ou CDA (Central de Ajuda Site Latam)","") | W11: =$Z$2&H11&$Y$2&H11 -> &entry.1585267062=&entry.409012661=
F12: =N12 -> https://docs.google.com/forms/d/e/1FAIpQLSdL6XnoqNKTAw7dlsIr2ZZmRPtlLw-idLKWanRUaG1h56cebg/viewform?entry.1095270279=&entry.191341224=&entry.2101494904=Dúvida&entry.1095270279=&entry.950207260=&entry.237710686=&entry.1585267062=&entry.409012661= | G12: <-- clica copie e cole lá no navegador | K12: Passageiro com Necessidades de Ordem Intelectual leve e Independentes | N12: =$R$2&O12 -> https://docs.google.com/forms/d/e/1FAIpQLSdL6XnoqNKTAw7dlsIr2ZZmRPtlLw-idLKWanRUaG1h56cebg/viewform?entry.1095270279=&entry.191341224=&entry.2101494904=Dúvida&entry.1095270279=&entry.950207260=&entry.237710686=&entry.1585267062=&entry.409012661= | O12: =$Q$2&A12&$Q$3&C12&$Q$4&$S12&$Q$2&$Q$5&D12&$Q$6&D12&$T12&$U12&$V12&W12 -> entry.1095270279=&entry.191341224=&entry.2101494904=Dúvida&entry.1095270279=&entry.950207260=&entry.237710686=&entry.1585267062=&entry.409012661= | S12: =IF(COUNTIF($K$2:$K$21,D12)>0,"Execução&","Dúvida&") -> Dúvida& | T12: =IF(E12="BOM","&entry.2006968231=O agente demonstra conhecer o processo, mas aciona para validar a informação.","") | U12: =IF(E12="MEDIANO","&entry.2006968231=O agente demonstra não saber como conduzir a situação com o cliente&entry.2006968231=Falta de conhecimento da ferramenta","") | V12: =IF(E12="RUIM","&entry.2006968231=O agente demonstra não saber como conduzir a situação com o cliente&entry.2006968231=Falta de conhecimento da ferramenta&entry.2006968231=Não ter realizado a leitura no PIC ou CDA (Central de Ajuda Site Latam)&entry.2006968231=Não saber "&"interpretar a informação no PIC ou CDA (Central de Ajuda Site Latam)","") | W12: =$Z$2&H12&$Y$2&H12 -> &entry.1585267062=&entry.409012661=
F13: =N13 -> https://docs.google.com/forms/d/e/1FAIpQLSdL6XnoqNKTAw7dlsIr2ZZmRPtlLw-idLKWanRUaG1h56cebg/viewform?entry.1095270279=&entry.191341224=&entry.2101494904=Dúvida&entry.1095270279=&entry.950207260=&entry.237710686=&entry.1585267062=&entry.409012661= | G13: <-- clica copie e cole lá no navegador | K13: Passageiros com Necessidades Especiais de Ordem Sensorial (Visual ou Auditiva) Parcial ou Total | N13: =$R$2&O13 -> https://docs.google.com/forms/d/e/1FAIpQLSdL6XnoqNKTAw7dlsIr2ZZmRPtlLw-idLKWanRUaG1h56cebg/viewform?entry.1095270279=&entry.191341224=&entry.2101494904=Dúvida&entry.1095270279=&entry.950207260=&entry.237710686=&entry.1585267062=&entry.409012661= | O13: =$Q$2&A13&$Q$3&C13&$Q$4&$S13&$Q$2&$Q$5&D13&$Q$6&D13&$T13&$U13&$V13&W13 -> entry.1095270279=&entry.191341224=&entry.2101494904=Dúvida&entry.1095270279=&entry.950207260=&entry.237710686=&entry.1585267062=&entry.409012661= | S13: =IF(COUNTIF($K$2:$K$21,D13)>0,"Execução&","Dúvida&") -> Dúvida& | T13: =IF(E13="BOM","&entry.2006968231=O agente demonstra conhecer o processo, mas aciona para validar a informação.","") | U13: =IF(E13="MEDIANO","&entry.2006968231=O agente demonstra não saber como conduzir a situação com o cliente&entry.2006968231=Falta de conhecimento da ferramenta","") | V13: =IF(E13="RUIM","&entry.2006968231=O agente demonstra não saber como conduzir a situação com o cliente&entry.2006968231=Falta de conhecimento da ferramenta&entry.2006968231=Não ter realizado a leitura no PIC ou CDA (Central de Ajuda Site Latam)&entry.2006968231=Não saber "&"interpretar a informação no PIC ou CDA (Central de Ajuda Site Latam)","") | W13: =$Z$2&H13&$Y$2&H13 -> &entry.1585267062=&entry.409012661=
F14: =N14 -> https://docs.google.com/forms/d/e/1FAIpQLSdL6XnoqNKTAw7dlsIr2ZZmRPtlLw-idLKWanRUaG1h56cebg/viewform?entry.1095270279=&entry.191341224=&entry.2101494904=Dúvida&entry.1095270279=&entry.950207260=&entry.237710686=&entry.1585267062=&entry.409012661= | G14: <-- clica copie e cole lá no navegador | K14: Reclamação por Erro de Executivo | N14: =$R$2&O14 -> https://docs.google.com/forms/d/e/1FAIpQLSdL6XnoqNKTAw7dlsIr2ZZmRPtlLw-idLKWanRUaG1h56cebg/viewform?entry.1095270279=&entry.191341224=&entry.2101494904=Dúvida&entry.1095270279=&entry.950207260=&entry.237710686=&entry.1585267062=&entry.409012661= | O14: =$Q$2&A14&$Q$3&C14&$Q$4&$S14&$Q$2&$Q$5&D14&$Q$6&D14&$T14&$U14&$V14&W14 -> entry.1095270279=&entry.191341224=&entry.2101494904=Dúvida&entry.1095270279=&entry.950207260=&entry.237710686=&entry.1585267062=&entry.409012661= | S14: =IF(COUNTIF($K$2:$K$21,D14)>0,"Execução&","Dúvida&") -> Dúvida& | T14: =IF(E14="BOM","&entry.2006968231=O agente demonstra conhecer o processo, mas aciona para validar a informação.","") | U14: =IF(E14="MEDIANO","&entry.2006968231=O agente demonstra não saber como conduzir a situação com o cliente&entry.2006968231=Falta de conhecimento da ferramenta","") | V14: =IF(E14="RUIM","&entry.2006968231=O agente demonstra não saber como conduzir a situação com o cliente&entry.2006968231=Falta de conhecimento da ferramenta&entry.2006968231=Não ter realizado a leitura no PIC ou CDA (Central de Ajuda Site Latam)&entry.2006968231=Não saber "&"interpretar a informação no PIC ou CDA (Central de Ajuda Site Latam)","") | W14: =$Z$2&H14&$Y$2&H14 -> &entry.1585267062=&entry.409012661=
F15: =N15 -> https://docs.google.com/forms/d/e/1FAIpQLSdL6XnoqNKTAw7dlsIr2ZZmRPtlLw-idLKWanRUaG1h56cebg/viewform?entry.1095270279=&entry.191341224=&entry.2101494904=Dúvida&entry.1095270279=&entry.950207260=&entry.237710686=&entry.1585267062=&entry.409012661= | G15: <-- clica copie e cole lá no navegador | K15: Retomar Espaços (até 3 horas após retirada do voo) | N15: =$R$2&O15 -> https://docs.google.com/forms/d/e/1FAIpQLSdL6XnoqNKTAw7dlsIr2ZZmRPtlLw-idLKWanRUaG1h56cebg/viewform?entry.1095270279=&entry.191341224=&entry.2101494904=Dúvida&entry.1095270279=&entry.950207260=&entry.237710686=&entry.1585267062=&entry.409012661= | O15: =$Q$2&A15&$Q$3&C15&$Q$4&$S15&$Q$2&$Q$5&D15&$Q$6&D15&$T15&$U15&$V15&W15 -> entry.1095270279=&entry.191341224=&entry.2101494904=Dúvida&entry.1095270279=&entry.950207260=&entry.237710686=&entry.1585267062=&entry.409012661= | S15: =IF(COUNTIF($K$2:$K$21,D15)>0,"Execução&","Dúvida&") -> Dúvida& | T15: =IF(E15="BOM","&entry.2006968231=O agente demonstra conhecer o processo, mas aciona para validar a informação.","") | U15: =IF(E15="MEDIANO","&entry.2006968231=O agente demonstra não saber como conduzir a situação com o cliente&entry.2006968231=Falta de conhecimento da ferramenta","") | V15: =IF(E15="RUIM","&entry.2006968231=O agente demonstra não saber como conduzir a situação com o cliente&entry.2006968231=Falta de conhecimento da ferramenta&entry.2006968231=Não ter realizado a leitura no PIC ou CDA (Central de Ajuda Site Latam)&entry.2006968231=Não saber "&"interpretar a informação no PIC ou CDA (Central de Ajuda Site Latam)","") | W15: =$Z$2&H15&$Y$2&H15 -> &entry.1585267062=&entry.409012661=
F16: =N16 -> https://docs.google.com/forms/d/e/1FAIpQLSdL6XnoqNKTAw7dlsIr2ZZmRPtlLw-idLKWanRUaG1h56cebg/viewform?entry.1095270279=&entry.191341224=&entry.2101494904=Dúvida&entry.1095270279=&entry.950207260=&entry.237710686=&entry.1585267062=&entry.409012661= | G16: <-- clica copie e cole lá no navegador | K16: Retomar Espaço (Falso No show) | N16: =$R$2&O16 -> https://docs.google.com/forms/d/e/1FAIpQLSdL6XnoqNKTAw7dlsIr2ZZmRPtlLw-idLKWanRUaG1h56cebg/viewform?entry.1095270279=&entry.191341224=&entry.2101494904=Dúvida&entry.1095270279=&entry.950207260=&entry.237710686=&entry.1585267062=&entry.409012661= | O16: =$Q$2&A16&$Q$3&C16&$Q$4&$S16&$Q$2&$Q$5&D16&$Q$6&D16&$T16&$U16&$V16&W16 -> entry.1095270279=&entry.191341224=&entry.2101494904=Dúvida&entry.1095270279=&entry.950207260=&entry.237710686=&entry.1585267062=&entry.409012661= | S16: =IF(COUNTIF($K$2:$K$21,D16)>0,"Execução&","Dúvida&") -> Dúvida& | T16: =IF(E16="BOM","&entry.2006968231=O agente demonstra conhecer o processo, mas aciona para validar a informação.","") | U16: =IF(E16="MEDIANO","&entry.2006968231=O agente demonstra não saber como conduzir a situação com o cliente&entry.2006968231=Falta de conhecimento da ferramenta","") | V16: =IF(E16="RUIM","&entry.2006968231=O agente demonstra não saber como conduzir a situação com o cliente&entry.2006968231=Falta de conhecimento da ferramenta&entry.2006968231=Não ter realizado a leitura no PIC ou CDA (Central de Ajuda Site Latam)&entry.2006968231=Não saber "&"interpretar a informação no PIC ou CDA (Central de Ajuda Site Latam)","") | W16: =$Z$2&H16&$Y$2&H16 -> &entry.1585267062=&entry.409012661=
F17: =N17 -> https://docs.google.com/forms/d/e/1FAIpQLSdL6XnoqNKTAw7dlsIr2ZZmRPtlLw-idLKWanRUaG1h56cebg/viewform?entry.1095270279=&entry.191341224=&entry.2101494904=Dúvida&entry.1095270279=&entry.950207260=&entry.237710686=&entry.1585267062=&entry.409012661= | G17: <-- clica copie e cole lá no navegador | K17: Retomar Espaço (outros temas) | N17: =$R$2&O17 -> https://docs.google.com/forms/d/e/1FAIpQLSdL6XnoqNKTAw7dlsIr2ZZmRPtlLw-idLKWanRUaG1h56cebg/viewform?entry.1095270279=&entry.191341224=&entry.2101494904=Dúvida&entry.1095270279=&entry.950207260=&entry.237710686=&entry.1585267062=&entry.409012661= | O17: =$Q$2&A17&$Q$3&C17&$Q$4&$S17&$Q$2&$Q$5&D17&$Q$6&D17&$T17&$U17&$V17&W17 -> entry.1095270279=&entry.191341224=&entry.2101494904=Dúvida&entry.1095270279=&entry.950207260=&entry.237710686=&entry.1585267062=&entry.409012661= | S17: =IF(COUNTIF($K$2:$K$21,D17)>0,"Execução&","Dúvida&") -> Dúvida& | T17: =IF(E17="BOM","&entry.2006968231=O agente demonstra conhecer o processo, mas aciona para validar a informação.","") | U17: =IF(E17="MEDIANO","&entry.2006968231=O agente demonstra não saber como conduzir a situação com o cliente&entry.2006968231=Falta de conhecimento da ferramenta","") | V17: =IF(E17="RUIM","&entry.2006968231=O agente demonstra não saber como conduzir a situação com o cliente&entry.2006968231=Falta de conhecimento da ferramenta&entry.2006968231=Não ter realizado a leitura no PIC ou CDA (Central de Ajuda Site Latam)&entry.2006968231=Não saber "&"interpretar a informação no PIC ou CDA (Central de Ajuda Site Latam)","") | W17: =$Z$2&H17&$Y$2&H17 -> &entry.1585267062=&entry.409012661=
F18: =N18 -> https://docs.google.com/forms/d/e/1FAIpQLSdL6XnoqNKTAw7dlsIr2ZZmRPtlLw-idLKWanRUaG1h56cebg/viewform?entry.1095270279=&entry.191341224=&entry.2101494904=Dúvida&entry.1095270279=&entry.950207260=&entry.237710686=&entry.1585267062=&entry.409012661= | G18: <-- clica copie e cole lá no navegador | K18: Solicitação para Dispositivos de Assistência Respiratória | N18: =$R$2&O18 -> https://docs.google.com/forms/d/e/1FAIpQLSdL6XnoqNKTAw7dlsIr2ZZmRPtlLw-idLKWanRUaG1h56cebg/viewform?entry.1095270279=&entry.191341224=&entry.2101494904=Dúvida&entry.1095270279=&entry.950207260=&entry.237710686=&entry.1585267062=&entry.409012661= | O18: =$Q$2&A18&$Q$3&C18&$Q$4&$S18&$Q$2&$Q$5&D18&$Q$6&D18&$T18&$U18&$V18&W18 -> entry.1095270279=&entry.191341224=&entry.2101494904=Dúvida&entry.1095270279=&entry.950207260=&entry.237710686=&entry.1585267062=&entry.409012661= | S18: =IF(COUNTIF($K$2:$K$21,D18)>0,"Execução&","Dúvida&") -> Dúvida& | T18: =IF(E18="BOM","&entry.2006968231=O agente demonstra conhecer o processo, mas aciona para validar a informação.","") | U18: =IF(E18="MEDIANO","&entry.2006968231=O agente demonstra não saber como conduzir a situação com o cliente&entry.2006968231=Falta de conhecimento da ferramenta","") | V18: =IF(E18="RUIM","&entry.2006968231=O agente demonstra não saber como conduzir a situação com o cliente&entry.2006968231=Falta de conhecimento da ferramenta&entry.2006968231=Não ter realizado a leitura no PIC ou CDA (Central de Ajuda Site Latam)&entry.2006968231=Não saber "&"interpretar a informação no PIC ou CDA (Central de Ajuda Site Latam)","") | W18: =$Z$2&H18&$Y$2&H18 -> &entry.1585267062=&entry.409012661=
F19: =N19 -> https://docs.google.com/forms/d/e/1FAIpQLSdL6XnoqNKTAw7dlsIr2ZZmRPtlLw-idLKWanRUaG1h56cebg/viewform?entry.1095270279=&entry.191341224=&entry.2101494904=Dúvida&entry.1095270279=&entry.950207260=&entry.237710686=&entry.1585267062=&entry.409012661= | G19: <-- clica copie e cole lá no navegador | K19: Troca de data, voo e/ou rerouting - Alteração Involuntária | N19: =$R$2&O19 -> https://docs.google.com/forms/d/e/1FAIpQLSdL6XnoqNKTAw7dlsIr2ZZmRPtlLw-idLKWanRUaG1h56cebg/viewform?entry.1095270279=&entry.191341224=&entry.2101494904=Dúvida&entry.1095270279=&entry.950207260=&entry.237710686=&entry.1585267062=&entry.409012661= | O19: =$Q$2&A19&$Q$3&C19&$Q$4&$S19&$Q$2&$Q$5&D19&$Q$6&D19&$T19&$U19&$V19&W19 -> entry.1095270279=&entry.191341224=&entry.2101494904=Dúvida&entry.1095270279=&entry.950207260=&entry.237710686=&entry.1585267062=&entry.409012661= | S19: =IF(COUNTIF($K$2:$K$21,D19)>0,"Execução&","Dúvida&") -> Dúvida& | T19: =IF(E19="BOM","&entry.2006968231=O agente demonstra conhecer o processo, mas aciona para validar a informação.","") | U19: =IF(E19="MEDIANO","&entry.2006968231=O agente demonstra não saber como conduzir a situação com o cliente&entry.2006968231=Falta de conhecimento da ferramenta","") | V19: =IF(E19="RUIM","&entry.2006968231=O agente demonstra não saber como conduzir a situação com o cliente&entry.2006968231=Falta de conhecimento da ferramenta&entry.2006968231=Não ter realizado a leitura no PIC ou CDA (Central de Ajuda Site Latam)&entry.2006968231=Não saber "&"interpretar a informação no PIC ou CDA (Central de Ajuda Site Latam)","") | W19: =$Z$2&H19&$Y$2&H19 -> &entry.1585267062=&entry.409012661=
... F37: =N37 -> https://docs.google.com/forms/d/e/1FAIpQLSdL6XnoqNKTAw7dlsIr2ZZmRPtlLw-idLKWanRUaG1h56cebg/viewform?entry.1095270279=&entry.191341224=&entry.2101494904=Dúvida&entry.1095270279=&entry.950207260=&entry.237710686=&entry.1585267062=&entry.409012661= | G37: <-- clica copie e cole lá no navegador | K37: Upgrade (postulação por cupom ou leilão, e reemissão com custo para troca de cabine) | N37: =$R$2&O37 -> https://docs.google.com/forms/d/e/1FAIpQLSdL6XnoqNKTAw7dlsIr2ZZmRPtlLw-idLKWanRUaG1h56cebg/viewform?entry.1095270279=&entry.191341224=&entry.2101494904=Dúvida&entry.1095270279=&entry.950207260=&entry.237710686=&entry.1585267062=&entry.409012661= | O37: =$Q$2&A37&$Q$3&C37&$Q$4&$S37&$Q$2&$Q$5&D37&$Q$6&D37&$T37&$U37&$V37&W37 -> entry.1095270279=&entry.191341224=&entry.2101494904=Dúvida&entry.1095270279=&entry.950207260=&entry.237710686=&entry.1585267062=&entry.409012661= | S37: =IF(COUNTIF($K$2:$K$21,D37)>0,"Execução&","Dúvida&") -> Dúvida& | T37: =IF(E37="BOM","&entry.2006968231=O agente demonstra conhecer o processo, mas aciona para validar a informação.","") | U37: =IF(E37="MEDIANO","&entry.2006968231=O agente demonstra não saber como conduzir a situação com o cliente&entry.2006968231=Falta de conhecimento da ferramenta","") | V37: =IF(E37="RUIM","&entry.2006968231=O agente demonstra não saber como conduzir a situação com o cliente&entry.2006968231=Falta de conhecimento da ferramenta&entry.2006968231=Não ter realizado a leitura no PIC ou CDA (Central de Ajuda Site Latam)&entry.2006968231=Não saber "&"interpretar a informação no PIC ou CDA (Central de Ajuda Site Latam)","") | W37: =$Z$2&H37&$Y$2&H37 -> &entry.1585267062=&entry.409012661=
F38: =N38 -> https://docs.google.com/forms/d/e/1FAIpQLSdL6XnoqNKTAw7dlsIr2ZZmRPtlLw-idLKWanRUaG1h56cebg/viewform?entry.1095270279=&entry.191341224=&entry.2101494904=Dúvida&entry.1095270279=&entry.950207260=&entry.237710686=&entry.1585267062=&entry.409012661= | G38: <-- clica copie e cole lá no navegador | N38: =$R$2&O38 -> https://docs.google.com/forms/d/e/1FAIpQLSdL6XnoqNKTAw7dlsIr2ZZmRPtlLw-idLKWanRUaG1h56cebg/viewform?entry.1095270279=&entry.191341224=&entry.2101494904=Dúvida&entry.1095270279=&entry.950207260=&entry.237710686=&entry.1585267062=&entry.409012661= | O38: =$Q$2&A38&$Q$3&C38&$Q$4&$S38&$Q$2&$Q$5&D38&$Q$6&D38&$T38&$U38&$V38&W38 -> entry.1095270279=&entry.191341224=&entry.2101494904=Dúvida&entry.1095270279=&entry.950207260=&entry.237710686=&entry.1585267062=&entry.409012661= | S38: =IF(COUNTIF($K$2:$K$21,D38)>0,"Execução&","Dúvida&") -> Dúvida& | T38: =IF(E38="BOM","&entry.2006968231=O agente demonstra conhecer o processo, mas aciona para validar a informação.","") | U38: =IF(E38="MEDIANO","&entry.2006968231=O agente demonstra não saber como conduzir a situação com o cliente&entry.2006968231=Falta de conhecimento da ferramenta","") | V38: =IF(E38="RUIM","&entry.2006968231=O agente demonstra não saber como conduzir a situação com o cliente&entry.2006968231=Falta de conhecimento da ferramenta&entry.2006968231=Não ter realizado a leitura no PIC ou CDA (Central de Ajuda Site Latam)&entry.2006968231=Não saber "&"interpretar a informação no PIC ou CDA (Central de Ajuda Site Latam)","") | W38: =$Z$2&H38&$Y$2&H38 -> &entry.1585267062=&entry.409012661=
F39: =N39 -> https://docs.google.com/forms/d/e/1FAIpQLSdL6XnoqNKTAw7dlsIr2ZZmRPtlLw-idLKWanRUaG1h56cebg/viewform?entry.1095270279=&entry.191341224=&entry.2101494904=Dúvida&entry.1095270279=&entry.950207260=&entry.237710686=&entry.1585267062=&entry.409012661= | G39: <-- clica copie e cole lá no navegador | N39: =$R$2&O39 -> https://docs.google.com/forms/d/e/1FAIpQLSdL6XnoqNKTAw7dlsIr2ZZmRPtlLw-idLKWanRUaG1h56cebg/viewform?entry.1095270279=&entry.191341224=&entry.2101494904=Dúvida&entry.1095270279=&entry.950207260=&entry.237710686=&entry.1585267062=&entry.409012661= | O39: =$Q$2&A39&$Q$3&C39&$Q$4&$S39&$Q$2&$Q$5&D39&$Q$6&D39&$T39&$U39&$V39&W39 -> entry.1095270279=&entry.191341224=&entry.2101494904=Dúvida&entry.1095270279=&entry.950207260=&entry.237710686=&entry.1585267062=&entry.409012661= | S39: =IF(COUNTIF($K$2:$K$21,D39)>0,"Execução&","Dúvida&") -> Dúvida& | T39: =IF(E39="BOM","&entry.2006968231=O agente demonstra conhecer o processo, mas aciona para validar a informação.","") | U39: =IF(E39="MEDIANO","&entry.2006968231=O agente demonstra não saber como conduzir a situação com o cliente&entry.2006968231=Falta de conhecimento da ferramenta","") | V39: =IF(E39="RUIM","&entry.2006968231=O agente demonstra não saber como conduzir a situação com o cliente&entry.2006968231=Falta de conhecimento da ferramenta&entry.2006968231=Não ter realizado a leitura no PIC ou CDA (Central de Ajuda Site Latam)&entry.2006968231=Não saber "&"interpretar a informação no PIC ou CDA (Central de Ajuda Site Latam)","") | W39: =$Z$2&H39&$Y$2&H39 -> &entry.1585267062=&entry.409012661=
F40: =N40 -> https://docs.google.com/forms/d/e/1FAIpQLSdL6XnoqNKTAw7dlsIr2ZZmRPtlLw-idLKWanRUaG1h56cebg/viewform?entry.1095270279=&entry.191341224=&entry.2101494904=Dúvida&entry.1095270279=&entry.950207260=&entry.237710686=&entry.1585267062=&entry.409012661= | G40: <-- clica copie e cole lá no navegador | N40: =$R$2&O40 -> https://docs.google.com/forms/d/e/1FAIpQLSdL6XnoqNKTAw7dlsIr2ZZmRPtlLw-idLKWanRUaG1h56cebg/viewform?entry.1095270279=&entry.191341224=&entry.2101494904=Dúvida&entry.1095270279=&entry.950207260=&entry.237710686=&entry.1585267062=&entry.409012661= | O40: =$Q$2&A40&$Q$3&C40&$Q$4&$S40&$Q$2&$Q$5&D40&$Q$6&D40&$T40&$U40&$V40&W40 -> entry.1095270279=&entry.191341224=&entry.2101494904=Dúvida&entry.1095270279=&entry.950207260=&entry.237710686=&entry.1585267062=&entry.409012661= | S40: =IF(COUNTIF($K$2:$K$21,D40)>0,"Execução&","Dúvida&") -> Dúvida& | T40: =IF(E40="BOM","&entry.2006968231=O agente demonstra conhecer o processo, mas aciona para validar a informação.","") | U40: =IF(E40="MEDIANO","&entry.2006968231=O agente demonstra não saber como conduzir a situação com o cliente&entry.2006968231=Falta de conhecimento da ferramenta","") | V40: =IF(E40="RUIM","&entry.2006968231=O agente demonstra não saber como conduzir a situação com o cliente&entry.2006968231=Falta de conhecimento da ferramenta&entry.2006968231=Não ter realizado a leitura no PIC ou CDA (Central de Ajuda Site Latam)&entry.2006968231=Não saber "&"interpretar a informação no PIC ou CDA (Central de Ajuda Site Latam)","") | W40: =$Z$2&H40&$Y$2&H40 -> &entry.1585267062=&entry.409012661=
F41: =N41 -> https://docs.google.com/forms/d/e/1FAIpQLSdL6XnoqNKTAw7dlsIr2ZZmRPtlLw-idLKWanRUaG1h56cebg/viewform?entry.1095270279=&entry.191341224=&entry.2101494904=Dúvida&entry.1095270279=&entry.950207260=&entry.237710686=&entry.1585267062=&entry.409012661= | G41: <-- clica copie e cole lá no navegador | N41: =$R$2&O41 -> https://docs.google.com/forms/d/e/1FAIpQLSdL6XnoqNKTAw7dlsIr2ZZmRPtlLw-idLKWanRUaG1h56cebg/viewform?entry.1095270279=&entry.191341224=&entry.2101494904=Dúvida&entry.1095270279=&entry.950207260=&entry.237710686=&entry.1585267062=&entry.409012661= | O41: =$Q$2&A41&$Q$3&C41&$Q$4&$S41&$Q$2&$Q$5&D41&$Q$6&D41&$T41&$U41&$V41&W41 -> entry.1095270279=&entry.191341224=&entry.2101494904=Dúvida&entry.1095270279=&entry.950207260=&entry.237710686=&entry.1585267062=&entry.409012661= | S41: =IF(COUNTIF($K$2:$K$21,D41)>0,"Execução&","Dúvida&") -> Dúvida& | T41: =IF(E41="BOM","&entry.2006968231=O agente demonstra conhecer o processo, mas aciona para validar a informação.","") | U41: =IF(E41="MEDIANO","&entry.2006968231=O agente demonstra não saber como conduzir a situação com o cliente&entry.2006968231=Falta de conhecimento da ferramenta","") | V41: =IF(E41="RUIM","&entry.2006968231=O agente demonstra não saber como conduzir a situação com o cliente&entry.2006968231=Falta de conhecimento da ferramenta&entry.2006968231=Não ter realizado a leitura no PIC ou CDA (Central de Ajuda Site Latam)&entry.2006968231=Não saber "&"interpretar a informação no PIC ou CDA (Central de Ajuda Site Latam)","") | W41: =$Z$2&H41&$Y$2&H41 -> &entry.1585267062=&entry.409012661=
F42: =N42 -> https://docs.google.com/forms/d/e/1FAIpQLSdL6XnoqNKTAw7dlsIr2ZZmRPtlLw-idLKWanRUaG1h56cebg/viewform?entry.1095270279=&entry.191341224=&entry.2101494904=Dúvida&entry.1095270279=&entry.950207260=&entry.237710686=&entry.1585267062=&entry.409012661= | G42: <-- clica copie e cole lá no navegador | N42: =$R$2&O42 -> https://docs.google.com/forms/d/e/1FAIpQLSdL6XnoqNKTAw7dlsIr2ZZmRPtlLw-idLKWanRUaG1h56cebg/viewform?entry.1095270279=&entry.191341224=&entry.2101494904=Dúvida&entry.1095270279=&entry.950207260=&entry.237710686=&entry.1585267062=&entry.409012661= | O42: =$Q$2&A42&$Q$3&C42&$Q$4&$S42&$Q$2&$Q$5&D42&$Q$6&D42&$T42&$U42&$V42&W42 -> entry.1095270279=&entry.191341224=&entry.2101494904=Dúvida&entry.1095270279=&entry.950207260=&entry.237710686=&entry.1585267062=&entry.409012661= | S42: =IF(COUNTIF($K$2:$K$21,D42)>0,"Execução&","Dúvida&") -> Dúvida& | T42: =IF(E42="BOM","&entry.2006968231=O agente demonstra conhecer o processo, mas aciona para validar a informação.","") | U42: =IF(E42="MEDIANO","&entry.2006968231=O agente demonstra não saber como conduzir a situação com o cliente&entry.2006968231=Falta de conhecimento da ferramenta","") | V42: =IF(E42="RUIM","&entry.2006968231=O agente demonstra não saber como conduzir a situação com o cliente&entry.2006968231=Falta de conhecimento da ferramenta&entry.2006968231=Não ter realizado a leitura no PIC ou CDA (Central de Ajuda Site Latam)&entry.2006968231=Não saber "&"interpretar a informação no PIC ou CDA (Central de Ajuda Site Latam)","") | W42: =$Z$2&H42&$Y$2&H42 -> &entry.1585267062=&entry.409012661=
F43: =N43 -> https://docs.google.com/forms/d/e/1FAIpQLSdL6XnoqNKTAw7dlsIr2ZZmRPtlLw-idLKWanRUaG1h56cebg/viewform?entry.1095270279=&entry.191341224=&entry.2101494904=Dúvida&entry.1095270279=&entry.950207260=&entry.237710686=&entry.1585267062=&entry.409012661= | G43: <-- clica copie e cole lá no navegador | N43: =$R$2&O43 -> https://docs.google.com/forms/d/e/1FAIpQLSdL6XnoqNKTAw7dlsIr2ZZmRPtlLw-idLKWanRUaG1h56cebg/viewform?entry.1095270279=&entry.191341224=&entry.2101494904=Dúvida&entry.1095270279=&entry.950207260=&entry.237710686=&entry.1585267062=&entry.409012661= | O43: =$Q$2&A43&$Q$3&C43&$Q$4&$S43&$Q$2&$Q$5&D43&$Q$6&D43&$T43&$U43&$V43&W43 -> entry.1095270279=&entry.191341224=&entry.2101494904=Dúvida&entry.1095270279=&entry.950207260=&entry.237710686=&entry.1585267062=&entry.409012661= | S43: =IF(COUNTIF($K$2:$K$21,D43)>0,"Execução&","Dúvida&") -> Dúvida& | T43: =IF(E43="BOM","&entry.2006968231=O agente demonstra conhecer o processo, mas aciona para validar a informação.","") | U43: =IF(E43="MEDIANO","&entry.2006968231=O agente demonstra não saber como conduzir a situação com o cliente&entry.2006968231=Falta de conhecimento da ferramenta","") | V43: =IF(E43="RUIM","&entry.2006968231=O agente demonstra não saber como conduzir a situação com o cliente&entry.2006968231=Falta de conhecimento da ferramenta&entry.2006968231=Não ter realizado a leitura no PIC ou CDA (Central de Ajuda Site Latam)&entry.2006968231=Não saber "&"interpretar a informação no PIC ou CDA (Central de Ajuda Site Latam)","") | W43: =$Z$2&H43&$Y$2&H43 -> &entry.1585267062=&entry.409012661=
F44: =N44 -> https://docs.google.com/forms/d/e/1FAIpQLSdL6XnoqNKTAw7dlsIr2ZZmRPtlLw-idLKWanRUaG1h56cebg/viewform?entry.1095270279=&entry.191341224=&entry.2101494904=Dúvida&entry.1095270279=&entry.950207260=&entry.237710686=&entry.1585267062=&entry.409012661= | G44: <-- clica copie e cole lá no navegador | N44: =$R$2&O44 -> https://docs.google.com/forms/d/e/1FAIpQLSdL6XnoqNKTAw7dlsIr2ZZmRPtlLw-idLKWanRUaG1h56cebg/viewform?entry.1095270279=&entry.191341224=&entry.2101494904=Dúvida&entry.1095270279=&entry.950207260=&entry.237710686=&entry.1585267062=&entry.409012661= | O44: =$Q$2&A44&$Q$3&C44&$Q$4&$S44&$Q$2&$Q$5&D44&$Q$6&D44&$T44&$U44&$V44&W44 -> entry.1095270279=&entry.191341224=&entry.2101494904=Dúvida&entry.1095270279=&entry.950207260=&entry.237710686=&entry.1585267062=&entry.409012661= | S44: =IF(COUNTIF($K$2:$K$21,D44)>0,"Execução&","Dúvida&") -> Dúvida& | T44: =IF(E44="BOM","&entry.2006968231=O agente demonstra conhecer o processo, mas aciona para validar a informação.","") | U44: =IF(E44="MEDIANO","&entry.2006968231=O agente demonstra não saber como conduzir a situação com o cliente&entry.2006968231=Falta de conhecimento da ferramenta","") | V44: =IF(E44="RUIM","&entry.2006968231=O agente demonstra não saber como conduzir a situação com o cliente&entry.2006968231=Falta de conhecimento da ferramenta&entry.2006968231=Não ter realizado a leitura no PIC ou CDA (Central de Ajuda Site Latam)&entry.2006968231=Não saber "&"interpretar a informação no PIC ou CDA (Central de Ajuda Site Latam)","") | W44: =$Z$2&H44&$Y$2&H44 -> &entry.1585267062=&entry.409012661=
F45: =N45 -> https://docs.google.com/forms/d/e/1FAIpQLSdL6XnoqNKTAw7dlsIr2ZZmRPtlLw-idLKWanRUaG1h56cebg/viewform?entry.1095270279=&entry.191341224=&entry.2101494904=Dúvida&entry.1095270279=&entry.950207260=&entry.237710686=&entry.1585267062=&entry.409012661= | G45: <-- clica copie e cole lá no navegador | N45: =$R$2&O45 -> https://docs.google.com/forms/d/e/1FAIpQLSdL6XnoqNKTAw7dlsIr2ZZmRPtlLw-idLKWanRUaG1h56cebg/viewform?entry.1095270279=&entry.191341224=&entry.2101494904=Dúvida&entry.1095270279=&entry.950207260=&entry.237710686=&entry.1585267062=&entry.409012661= | O45: =$Q$2&A45&$Q$3&C45&$Q$4&$S45&$Q$2&$Q$5&D45&$Q$6&D45&$T45&$U45&$V45&W45 -> entry.1095270279=&entry.191341224=&entry.2101494904=Dúvida&entry.1095270279=&entry.950207260=&entry.237710686=&entry.1585267062=&entry.409012661= | S45: =IF(COUNTIF($K$2:$K$21,D45)>0,"Execução&","Dúvida&") -> Dúvida& | T45: =IF(E45="BOM","&entry.2006968231=O agente demonstra conhecer o processo, mas aciona para validar a informação.","") | U45: =IF(E45="MEDIANO","&entry.2006968231=O agente demonstra não saber como conduzir a situação com o cliente&entry.2006968231=Falta de conhecimento da ferramenta","") | V45: =IF(E45="RUIM","&entry.2006968231=O agente demonstra não saber como conduzir a situação com o cliente&entry.2006968231=Falta de conhecimento da ferramenta&entry.2006968231=Não ter realizado a leitura no PIC ou CDA (Central de Ajuda Site Latam)&entry.2006968231=Não saber "&"interpretar a informação no PIC ou CDA (Central de Ajuda Site Latam)","") | W45: =$Z$2&H45&$Y$2&H45 -> &entry.1585267062=&entry.409012661=
F46: =N46 -> https://docs.google.com/forms/d/e/1FAIpQLSdL6XnoqNKTAw7dlsIr2ZZmRPtlLw-idLKWanRUaG1h56cebg/viewform?entry.1095270279=&entry.191341224=&entry.2101494904=Dúvida&entry.1095270279=&entry.950207260=&entry.237710686=&entry.1585267062=&entry.409012661= | G46: <-- clica copie e cole lá no navegador | N46: =$R$2&O46 -> https://docs.google.com/forms/d/e/1FAIpQLSdL6XnoqNKTAw7dlsIr2ZZmRPtlLw-idLKWanRUaG1h56cebg/viewform?entry.1095270279=&entry.191341224=&entry.2101494904=Dúvida&entry.1095270279=&entry.950207260=&entry.237710686=&entry.1585267062=&entry.409012661= | O46: =$Q$2&A46&$Q$3&C46&$Q$4&$S46&$Q$2&$Q$5&D46&$Q$6&D46&$T46&$U46&$V46&W46 -> entry.1095270279=&entry.191341224=&entry.2101494904=Dúvida&entry.1095270279=&entry.950207260=&entry.237710686=&entry.1585267062=&entry.409012661= | S46: =IF(COUNTIF($K$2:$K$21,D46)>0,"Execução&","Dúvida&") -> Dúvida& | T46: =IF(E46="BOM","&entry.2006968231=O agente demonstra conhecer o processo, mas aciona para validar a informação.","") | U46: =IF(E46="MEDIANO","&entry.2006968231=O agente demonstra não saber como conduzir a situação com o cliente&entry.2006968231=Falta de conhecimento da ferramenta","") | V46: =IF(E46="RUIM","&entry.2006968231=O agente demonstra não saber como conduzir a situação com o cliente&entry.2006968231=Falta de conhecimento da ferramenta&entry.2006968231=Não ter realizado a leitura no PIC ou CDA (Central de Ajuda Site Latam)&entry.2006968231=Não saber "&"interpretar a informação no PIC ou CDA (Central de Ajuda Site Latam)","") | W46: =$Z$2&H46&$Y$2&H46 -> &entry.1585267062=&entry.409012661=
F47: =N47 -> https://docs.google.com/forms/d/e/1FAIpQLSdL6XnoqNKTAw7dlsIr2ZZmRPtlLw-idLKWanRUaG1h56cebg/viewform?entry.1095270279=&entry.191341224=&entry.2101494904=Dúvida&entry.1095270279=&entry.950207260=&entry.237710686=&entry.1585267062=&entry.409012661= | G47: <-- clica copie e cole lá no navegador | N47: =$R$2&O47 -> https://docs.google.com/forms/d/e/1FAIpQLSdL6XnoqNKTAw7dlsIr2ZZmRPtlLw-idLKWanRUaG1h56cebg/viewform?entry.1095270279=&entry.191341224=&entry.2101494904=Dúvida&entry.1095270279=&entry.950207260=&entry.237710686=&entry.1585267062=&entry.409012661= | O47: =$Q$2&A47&$Q$3&C47&$Q$4&$S47&$Q$2&$Q$5&D47&$Q$6&D47&$T47&$U47&$V47&W47 -> entry.1095270279=&entry.191341224=&entry.2101494904=Dúvida&entry.1095270279=&entry.950207260=&entry.237710686=&entry.1585267062=&entry.409012661= | S47: =IF(COUNTIF($K$2:$K$21,D47)>0,"Execução&","Dúvida&") -> Dúvida& | T47: =IF(E47="BOM","&entry.2006968231=O agente demonstra conhecer o processo, mas aciona para validar a informação.","") | U47: =IF(E47="MEDIANO","&entry.2006968231=O agente demonstra não saber como conduzir a situação com o cliente&entry.2006968231=Falta de conhecimento da ferramenta","") | V47: =IF(E47="RUIM","&entry.2006968231=O agente demonstra não saber como conduzir a situação com o cliente&entry.2006968231=Falta de conhecimento da ferramenta&entry.2006968231=Não ter realizado a leitura no PIC ou CDA (Central de Ajuda Site Latam)&entry.2006968231=Não saber "&"interpretar a informação no PIC ou CDA (Central de Ajuda Site Latam)","") | W47: =$Z$2&H47&$Y$2&H47 -> &entry.1585267062=&entry.409012661=
F48: =N48 -> https://docs.google.com/forms/d/e/1FAIpQLSdL6XnoqNKTAw7dlsIr2ZZmRPtlLw-idLKWanRUaG1h56cebg/viewform?entry.1095270279=&entry.191341224=&entry.2101494904=Dúvida&entry.1095270279=&entry.950207260=&entry.237710686=&entry.1585267062=&entry.409012661= | G48: <-- clica copie e cole lá no navegador | N48: =$R$2&O48 -> https://docs.google.com/forms/d/e/1FAIpQLSdL6XnoqNKTAw7dlsIr2ZZmRPtlLw-idLKWanRUaG1h56cebg/viewform?entry.1095270279=&entry.191341224=&entry.2101494904=Dúvida&entry.1095270279=&entry.950207260=&entry.237710686=&entry.1585267062=&entry.409012661= | O48: =$Q$2&A48&$Q$3&C48&$Q$4&$S48&$Q$2&$Q$5&D48&$Q$6&D48&$T48&$U48&$V48&W48 -> entry.1095270279=&entry.191341224=&entry.2101494904=Dúvida&entry.1095270279=&entry.950207260=&entry.237710686=&entry.1585267062=&entry.409012661= | S48: =IF(COUNTIF($K$2:$K$21,D48)>0,"Execução&","Dúvida&") -> Dúvida& | T48: =IF(E48="BOM","&entry.2006968231=O agente demonstra conhecer o processo, mas aciona para validar a informação.","") | U48: =IF(E48="MEDIANO","&entry.2006968231=O agente demonstra não saber como conduzir a situação com o cliente&entry.2006968231=Falta de conhecimento da ferramenta","") | V48: =IF(E48="RUIM","&entry.2006968231=O agente demonstra não saber como conduzir a situação com o cliente&entry.2006968231=Falta de conhecimento da ferramenta&entry.2006968231=Não ter realizado a leitura no PIC ou CDA (Central de Ajuda Site Latam)&entry.2006968231=Não saber "&"interpretar a informação no PIC ou CDA (Central de Ajuda Site Latam)","") | W48: =$Z$2&H48&$Y$2&H48 -> &entry.1585267062=&entry.409012661=
F49: =N49 -> https://docs.google.com/forms/d/e/1FAIpQLSdL6XnoqNKTAw7dlsIr2ZZmRPtlLw-idLKWanRUaG1h56cebg/viewform?entry.1095270279=&entry.191341224=&entry.2101494904=Dúvida&entry.1095270279=&entry.950207260=&entry.237710686=&entry.1585267062=&entry.409012661= | G49: <-- clica copie e cole lá no navegador | N49: =$R$2&O49 -> https://docs.google.com/forms/d/e/1FAIpQLSdL6XnoqNKTAw7dlsIr2ZZmRPtlLw-idLKWanRUaG1h56cebg/viewform?entry.1095270279=&entry.191341224=&entry.2101494904=Dúvida&entry.1095270279=&entry.950207260=&entry.237710686=&entry.1585267062=&entry.409012661= | O49: =$Q$2&A49&$Q$3&C49&$Q$4&$S49&$Q$2&$Q$5&D49&$Q$6&D49&$T49&$U49&$V49&W49 -> entry.1095270279=&entry.191341224=&entry.2101494904=Dúvida&entry.1095270279=&entry.950207260=&entry.237710686=&entry.1585267062=&entry.409012661= | S49: =IF(COUNTIF($K$2:$K$21,D49)>0,"Execução&","Dúvida&") -> Dúvida& | T49: =IF(E49="BOM","&entry.2006968231=O agente demonstra conhecer o processo, mas aciona para validar a informação.","") | U49: =IF(E49="MEDIANO","&entry.2006968231=O agente demonstra não saber como conduzir a situação com o cliente&entry.2006968231=Falta de conhecimento da ferramenta","") | V49: =IF(E49="RUIM","&entry.2006968231=O agente demonstra não saber como conduzir a situação com o cliente&entry.2006968231=Falta de conhecimento da ferramenta&entry.2006968231=Não ter realizado a leitura no PIC ou CDA (Central de Ajuda Site Latam)&entry.2006968231=Não saber "&"interpretar a informação no PIC ou CDA (Central de Ajuda Site Latam)","") | W49: =$Z$2&H49&$Y$2&H49 -> &entry.1585267062=&entry.409012661=
... F510: =N510 -> https://docs.google.com/forms/d/e/1FAIpQLSdL6XnoqNKTAw7dlsIr2ZZmRPtlLw-idLKWanRUaG1h56cebg/viewform?entry.1095270279=&entry.191341224=&entry.2101494904=Dúvida&entry.1095270279=&entry.950207260=&entry.237710686=&entry.1585267062=&entry.409012661= | G510: <-- clica copie e cole lá no navegador | N510: =$R$2&O510 -> https://docs.google.com/forms/d/e/1FAIpQLSdL6XnoqNKTAw7dlsIr2ZZmRPtlLw-idLKWanRUaG1h56cebg/viewform?entry.1095270279=&entry.191341224=&entry.2101494904=Dúvida&entry.1095270279=&entry.950207260=&entry.237710686=&entry.1585267062=&entry.409012661= | O510: =$Q$2&A510&$Q$3&C510&$Q$4&$S510&$Q$2&$Q$5&D510&$Q$6&D510&$T510&$U510&$V510&W510 -> entry.1095270279=&entry.191341224=&entry.2101494904=Dúvida&entry.1095270279=&entry.950207260=&entry.237710686=&entry.1585267062=&entry.409012661= | S510: =IF(COUNTIF($K$2:$K$21,D510)>0,"Execução&","Dúvida&") -> Dúvida& | T510: =IF(E510="BOM","&entry.2006968231=O agente demonstra conhecer o processo, mas aciona para validar a informação.","") | U510: =IF(E510="MEDIANO","&entry.2006968231=O agente demonstra não saber como conduzir a situação com o cliente&entry.2006968231=Falta de conhecimento da ferramenta","") | V510: =IF(E510="RUIM","&entry.2006968231=O agente demonstra não saber como conduzir a situação com o cliente&entry.2006968231=Falta de conhecimento da ferramenta&entry.2006968231=Não ter realizado a leitura no PIC ou CDA (Central de Ajuda Site Latam)&entry.2006968231=Não saber "&"interpretar a informação no PIC ou CDA (Central de Ajuda Site Latam)","") | W510: =$Z$2&H510&$Y$2&H510 -> &entry.1585267062=&entry.409012661=
F511: =N511 -> https://docs.google.com/forms/d/e/1FAIpQLSdL6XnoqNKTAw7dlsIr2ZZmRPtlLw-idLKWanRUaG1h56cebg/viewform?entry.1095270279=&entry.191341224=&entry.2101494904=Dúvida&entry.1095270279=&entry.950207260=&entry.237710686=&entry.1585267062=&entry.409012661= | G511: <-- clica copie e cole lá no navegador | N511: =$R$2&O511 -> https://docs.google.com/forms/d/e/1FAIpQLSdL6XnoqNKTAw7dlsIr2ZZmRPtlLw-idLKWanRUaG1h56cebg/viewform?entry.1095270279=&entry.191341224=&entry.2101494904=Dúvida&entry.1095270279=&entry.950207260=&entry.237710686=&entry.1585267062=&entry.409012661= | O511: =$Q$2&A511&$Q$3&C511&$Q$4&$S511&$Q$2&$Q$5&D511&$Q$6&D511&$T511&$U511&$V511&W511 -> entry.1095270279=&entry.191341224=&entry.2101494904=Dúvida&entry.1095270279=&entry.950207260=&entry.237710686=&entry.1585267062=&entry.409012661= | S511: =IF(COUNTIF($K$2:$K$21,D511)>0,"Execução&","Dúvida&") -> Dúvida& | T511: =IF(E511="BOM","&entry.2006968231=O agente demonstra conhecer o processo, mas aciona para validar a informação.","") | U511: =IF(E511="MEDIANO","&entry.2006968231=O agente demonstra não saber como conduzir a situação com o cliente&entry.2006968231=Falta de conhecimento da ferramenta","") | V511: =IF(E511="RUIM","&entry.2006968231=O agente demonstra não saber como conduzir a situação com o cliente&entry.2006968231=Falta de conhecimento da ferramenta&entry.2006968231=Não ter realizado a leitura no PIC ou CDA (Central de Ajuda Site Latam)&entry.2006968231=Não saber "&"interpretar a informação no PIC ou CDA (Central de Ajuda Site Latam)","") | W511: =$Z$2&H2&$Y$2&H2 -> &entry.1585267062=&entry.409012661=
F512: =N512 -> https://docs.google.com/forms/d/e/1FAIpQLSdL6XnoqNKTAw7dlsIr2ZZmRPtlLw-idLKWanRUaG1h56cebg/viewform?entry.1095270279=&entry.191341224=&entry.2101494904=Dúvida&entry.1095270279=&entry.950207260=&entry.237710686=&entry.1585267062=&entry.409012661= | G512: <-- clica copie e cole lá no navegador | N512: =$R$2&O512 -> https://docs.google.com/forms/d/e/1FAIpQLSdL6XnoqNKTAw7dlsIr2ZZmRPtlLw-idLKWanRUaG1h56cebg/viewform?entry.1095270279=&entry.191341224=&entry.2101494904=Dúvida&entry.1095270279=&entry.950207260=&entry.237710686=&entry.1585267062=&entry.409012661= | O512: =$Q$2&A512&$Q$3&C512&$Q$4&$S512&$Q$2&$Q$5&D512&$Q$6&D512&$T512&$U512&$V512&W512 -> entry.1095270279=&entry.191341224=&entry.2101494904=Dúvida&entry.1095270279=&entry.950207260=&entry.237710686=&entry.1585267062=&entry.409012661= | S512: =IF(COUNTIF($K$2:$K$21,D512)>0,"Execução&","Dúvida&") -> Dúvida& | T512: =IF(E512="BOM","&entry.2006968231=O agente demonstra conhecer o processo, mas aciona para validar a informação.","") | U512: =IF(E512="MEDIANO","&entry.2006968231=O agente demonstra não saber como conduzir a situação com o cliente&entry.2006968231=Falta de conhecimento da ferramenta","") | V512: =IF(E512="RUIM","&entry.2006968231=O agente demonstra não saber como conduzir a situação com o cliente&entry.2006968231=Falta de conhecimento da ferramenta&entry.2006968231=Não ter realizado a leitura no PIC ou CDA (Central de Ajuda Site Latam)&entry.2006968231=Não saber "&"interpretar a informação no PIC ou CDA (Central de Ajuda Site Latam)","") | W512: =$Z$2&H512&$Y$2&H512 -> &entry.1585267062=&entry.409012661=
F513: =N513 -> https://docs.google.com/forms/d/e/1FAIpQLSdL6XnoqNKTAw7dlsIr2ZZmRPtlLw-idLKWanRUaG1h56cebg/viewform?entry.1095270279=&entry.191341224=&entry.2101494904=Dúvida&entry.1095270279=&entry.950207260=&entry.237710686=&entry.1585267062=&entry.409012661= | G513: <-- clica copie e cole lá no navegador | N513: =$R$2&O513 -> https://docs.google.com/forms/d/e/1FAIpQLSdL6XnoqNKTAw7dlsIr2ZZmRPtlLw-idLKWanRUaG1h56cebg/viewform?entry.1095270279=&entry.191341224=&entry.2101494904=Dúvida&entry.1095270279=&entry.950207260=&entry.237710686=&entry.1585267062=&entry.409012661= | O513: =$Q$2&A513&$Q$3&C513&$Q$4&$S513&$Q$2&$Q$5&D513&$Q$6&D513&$T513&$U513&$V513&W513 -> entry.1095270279=&entry.191341224=&entry.2101494904=Dúvida&entry.1095270279=&entry.950207260=&entry.237710686=&entry.1585267062=&entry.409012661= | S513: =IF(COUNTIF($K$2:$K$21,D513)>0,"Execução&","Dúvida&") -> Dúvida& | T513: =IF(E513="BOM","&entry.2006968231=O agente demonstra conhecer o processo, mas aciona para validar a informação.","") | U513: =IF(E513="MEDIANO","&entry.2006968231=O agente demonstra não saber como conduzir a situação com o cliente&entry.2006968231=Falta de conhecimento da ferramenta","") | V513: =IF(E513="RUIM","&entry.2006968231=O agente demonstra não saber como conduzir a situação com o cliente&entry.2006968231=Falta de conhecimento da ferramenta&entry.2006968231=Não ter realizado a leitura no PIC ou CDA (Central de Ajuda Site Latam)&entry.2006968231=Não saber "&"interpretar a informação no PIC ou CDA (Central de Ajuda Site Latam)","") | W513: =$Z$2&H513&$Y$2&H513 -> &entry.1585267062=&entry.409012661=
F514: =N514 -> https://docs.google.com/forms/d/e/1FAIpQLSdL6XnoqNKTAw7dlsIr2ZZmRPtlLw-idLKWanRUaG1h56cebg/viewform?entry.1095270279=&entry.191341224=&entry.2101494904=Dúvida&entry.1095270279=&entry.950207260=&entry.237710686=&entry.1585267062=&entry.409012661= | G514: <-- clica copie e cole lá no navegador | N514: =$R$2&O514 -> https://docs.google.com/forms/d/e/1FAIpQLSdL6XnoqNKTAw7dlsIr2ZZmRPtlLw-idLKWanRUaG1h56cebg/viewform?entry.1095270279=&entry.191341224=&entry.2101494904=Dúvida&entry.1095270279=&entry.950207260=&entry.237710686=&entry.1585267062=&entry.409012661= | O514: =$Q$2&A514&$Q$3&C514&$Q$4&$S514&$Q$2&$Q$5&D514&$Q$6&D514&$T514&$U514&$V514&W514 -> entry.1095270279=&entry.191341224=&entry.2101494904=Dúvida&entry.1095270279=&entry.950207260=&entry.237710686=&entry.1585267062=&entry.409012661= | S514: =IF(COUNTIF($K$2:$K$21,D514)>0,"Execução&","Dúvida&") -> Dúvida& | T514: =IF(E514="BOM","&entry.2006968231=O agente demonstra conhecer o processo, mas aciona para validar a informação.","") | U514: =IF(E514="MEDIANO","&entry.2006968231=O agente demonstra não saber como conduzir a situação com o cliente&entry.2006968231=Falta de conhecimento da ferramenta","") | V514: =IF(E514="RUIM","&entry.2006968231=O agente demonstra não saber como conduzir a situação com o cliente&entry.2006968231=Falta de conhecimento da ferramenta&entry.2006968231=Não ter realizado a leitura no PIC ou CDA (Central de Ajuda Site Latam)&entry.2006968231=Não saber "&"interpretar a informação no PIC ou CDA (Central de Ajuda Site Latam)","") | W514: =$Z$2&H514&$Y$2&H514 -> &entry.1585267062=&entry.409012661=
F515: =N515 -> https://docs.google.com/forms/d/e/1FAIpQLSdL6XnoqNKTAw7dlsIr2ZZmRPtlLw-idLKWanRUaG1h56cebg/viewform?entry.1095270279=&entry.191341224=&entry.2101494904=Dúvida&entry.1095270279=&entry.950207260=&entry.237710686=&entry.1585267062=&entry.409012661= | G515: <-- clica copie e cole lá no navegador | N515: =$R$2&O515 -> https://docs.google.com/forms/d/e/1FAIpQLSdL6XnoqNKTAw7dlsIr2ZZmRPtlLw-idLKWanRUaG1h56cebg/viewform?entry.1095270279=&entry.191341224=&entry.2101494904=Dúvida&entry.1095270279=&entry.950207260=&entry.237710686=&entry.1585267062=&entry.409012661= | O515: =$Q$2&A515&$Q$3&C515&$Q$4&$S515&$Q$2&$Q$5&D515&$Q$6&D515&$T515&$U515&$V515&W515 -> entry.1095270279=&entry.191341224=&entry.2101494904=Dúvida&entry.1095270279=&entry.950207260=&entry.237710686=&entry.1585267062=&entry.409012661= | S515: =IF(COUNTIF($K$2:$K$21,D515)>0,"Execução&","Dúvida&") -> Dúvida& | T515: =IF(E515="BOM","&entry.2006968231=O agente demonstra conhecer o processo, mas aciona para validar a informação.","") | U515: =IF(E515="MEDIANO","&entry.2006968231=O agente demonstra não saber como conduzir a situação com o cliente&entry.2006968231=Falta de conhecimento da ferramenta","") | V515: =IF(E515="RUIM","&entry.2006968231=O agente demonstra não saber como conduzir a situação com o cliente&entry.2006968231=Falta de conhecimento da ferramenta&entry.2006968231=Não ter realizado a leitura no PIC ou CDA (Central de Ajuda Site Latam)&entry.2006968231=Não saber "&"interpretar a informação no PIC ou CDA (Central de Ajuda Site Latam)","") | W515: =$Z$2&H515&$Y$2&H515 -> &entry.1585267062=&entry.409012661=
F516: =N516 -> https://docs.google.com/forms/d/e/1FAIpQLSdL6XnoqNKTAw7dlsIr2ZZmRPtlLw-idLKWanRUaG1h56cebg/viewform?entry.1095270279=&entry.191341224=&entry.2101494904=Dúvida&entry.1095270279=&entry.950207260=&entry.237710686=&entry.1585267062=&entry.409012661= | G516: <-- clica copie e cole lá no navegador | N516: =$R$2&O516 -> https://docs.google.com/forms/d/e/1FAIpQLSdL6XnoqNKTAw7dlsIr2ZZmRPtlLw-idLKWanRUaG1h56cebg/viewform?entry.1095270279=&entry.191341224=&entry.2101494904=Dúvida&entry.1095270279=&entry.950207260=&entry.237710686=&entry.1585267062=&entry.409012661= | O516: =$Q$2&A516&$Q$3&C516&$Q$4&$S516&$Q$2&$Q$5&D516&$Q$6&D516&$T516&$U516&$V516&W516 -> entry.1095270279=&entry.191341224=&entry.2101494904=Dúvida&entry.1095270279=&entry.950207260=&entry.237710686=&entry.1585267062=&entry.409012661= | S516: =IF(COUNTIF($K$2:$K$21,D516)>0,"Execução&","Dúvida&") -> Dúvida& | T516: =IF(E516="BOM","&entry.2006968231=O agente demonstra conhecer o processo, mas aciona para validar a informação.","") | U516: =IF(E516="MEDIANO","&entry.2006968231=O agente demonstra não saber como conduzir a situação com o cliente&entry.2006968231=Falta de conhecimento da ferramenta","") | V516: =IF(E516="RUIM","&entry.2006968231=O agente demonstra não saber como conduzir a situação com o cliente&entry.2006968231=Falta de conhecimento da ferramenta&entry.2006968231=Não ter realizado a leitura no PIC ou CDA (Central de Ajuda Site Latam)&entry.2006968231=Não saber "&"interpretar a informação no PIC ou CDA (Central de Ajuda Site Latam)","") | W516: =$Z$2&H516&$Y$2&H516 -> &entry.1585267062=&entry.409012661=
F517: =N517 -> https://docs.google.com/forms/d/e/1FAIpQLSdL6XnoqNKTAw7dlsIr2ZZmRPtlLw-idLKWanRUaG1h56cebg/viewform?entry.1095270279=&entry.191341224=&entry.2101494904=Dúvida&entry.1095270279=&entry.950207260=&entry.237710686=&entry.1585267062=&entry.409012661= | G517: <-- clica copie e cole lá no navegador | N517: =$R$2&O517 -> https://docs.google.com/forms/d/e/1FAIpQLSdL6XnoqNKTAw7dlsIr2ZZmRPtlLw-idLKWanRUaG1h56cebg/viewform?entry.1095270279=&entry.191341224=&entry.2101494904=Dúvida&entry.1095270279=&entry.950207260=&entry.237710686=&entry.1585267062=&entry.409012661= | O517: =$Q$2&A517&$Q$3&C517&$Q$4&$S517&$Q$2&$Q$5&D517&$Q$6&D517&$T517&$U517&$V517&W517 -> entry.1095270279=&entry.191341224=&entry.2101494904=Dúvida&entry.1095270279=&entry.950207260=&entry.237710686=&entry.1585267062=&entry.409012661= | S517: =IF(COUNTIF($K$2:$K$21,D517)>0,"Execução&","Dúvida&") -> Dúvida& | T517: =IF(E517="BOM","&entry.2006968231=O agente demonstra conhecer o processo, mas aciona para validar a informação.","") | U517: =IF(E517="MEDIANO","&entry.2006968231=O agente demonstra não saber como conduzir a situação com o cliente&entry.2006968231=Falta de conhecimento da ferramenta","") | V517: =IF(E517="RUIM","&entry.2006968231=O agente demonstra não saber como conduzir a situação com o cliente&entry.2006968231=Falta de conhecimento da ferramenta&entry.2006968231=Não ter realizado a leitura no PIC ou CDA (Central de Ajuda Site Latam)&entry.2006968231=Não saber "&"interpretar a informação no PIC ou CDA (Central de Ajuda Site Latam)","") | W517: =$Z$2&H517&$Y$2&H517 -> &entry.1585267062=&entry.409012661=
F518: =N518 -> https://docs.google.com/forms/d/e/1FAIpQLSdL6XnoqNKTAw7dlsIr2ZZmRPtlLw-idLKWanRUaG1h56cebg/viewform?entry.1095270279=&entry.191341224=&entry.2101494904=Dúvida&entry.1095270279=&entry.950207260=&entry.237710686=&entry.1585267062=&entry.409012661= | G518: <-- clica copie e cole lá no navegador | N518: =$R$2&O518 -> https://docs.google.com/forms/d/e/1FAIpQLSdL6XnoqNKTAw7dlsIr2ZZmRPtlLw-idLKWanRUaG1h56cebg/viewform?entry.1095270279=&entry.191341224=&entry.2101494904=Dúvida&entry.1095270279=&entry.950207260=&entry.237710686=&entry.1585267062=&entry.409012661= | O518: =$Q$2&A518&$Q$3&C518&$Q$4&$S518&$Q$2&$Q$5&D518&$Q$6&D518&$T518&$U518&$V518&W518 -> entry.1095270279=&entry.191341224=&entry.2101494904=Dúvida&entry.1095270279=&entry.950207260=&entry.237710686=&entry.1585267062=&entry.409012661= | S518: =IF(COUNTIF($K$2:$K$21,D518)>0,"Execução&","Dúvida&") -> Dúvida& | T518: =IF(E518="BOM","&entry.2006968231=O agente demonstra conhecer o processo, mas aciona para validar a informação.","") | U518: =IF(E518="MEDIANO","&entry.2006968231=O agente demonstra não saber como conduzir a situação com o cliente&entry.2006968231=Falta de conhecimento da ferramenta","") | V518: =IF(E518="RUIM","&entry.2006968231=O agente demonstra não saber como conduzir a situação com o cliente&entry.2006968231=Falta de conhecimento da ferramenta&entry.2006968231=Não ter realizado a leitura no PIC ou CDA (Central de Ajuda Site Latam)&entry.2006968231=Não saber "&"interpretar a informação no PIC ou CDA (Central de Ajuda Site Latam)","") | W518: =$Z$2&H518&$Y$2&H518 -> &entry.1585267062=&entry.409012661=
F519: =N519 -> https://docs.google.com/forms/d/e/1FAIpQLSdL6XnoqNKTAw7dlsIr2ZZmRPtlLw-idLKWanRUaG1h56cebg/viewform?entry.1095270279=&entry.191341224=&entry.2101494904=Dúvida&entry.1095270279=&entry.950207260=&entry.237710686=&entry.1585267062=&entry.409012661= | G519: <-- clica copie e cole lá no navegador | N519: =$R$2&O519 -> https://docs.google.com/forms/d/e/1FAIpQLSdL6XnoqNKTAw7dlsIr2ZZmRPtlLw-idLKWanRUaG1h56cebg/viewform?entry.1095270279=&entry.191341224=&entry.2101494904=Dúvida&entry.1095270279=&entry.950207260=&entry.237710686=&entry.1585267062=&entry.409012661= | O519: =$Q$2&A519&$Q$3&C519&$Q$4&$S519&$Q$2&$Q$5&D519&$Q$6&D519&$T519&$U519&$V519&W519 -> entry.1095270279=&entry.191341224=&entry.2101494904=Dúvida&entry.1095270279=&entry.950207260=&entry.237710686=&entry.1585267062=&entry.409012661= | S519: =IF(COUNTIF($K$2:$K$21,D519)>0,"Execução&","Dúvida&") -> Dúvida& | T519: =IF(E519="BOM","&entry.2006968231=O agente demonstra conhecer o processo, mas aciona para validar a informação.","") | U519: =IF(E519="MEDIANO","&entry.2006968231=O agente demonstra não saber como conduzir a situação com o cliente&entry.2006968231=Falta de conhecimento da ferramenta","") | V519: =IF(E519="RUIM","&entry.2006968231=O agente demonstra não saber como conduzir a situação com o cliente&entry.2006968231=Falta de conhecimento da ferramenta&entry.2006968231=Não ter realizado a leitura no PIC ou CDA (Central de Ajuda Site Latam)&entry.2006968231=Não saber "&"interpretar a informação no PIC ou CDA (Central de Ajuda Site Latam)","") | W519: =$Z$2&H519&$Y$2&H519 -> &entry.1585267062=&entry.409012661=
F520: =N520 -> https://docs.google.com/forms/d/e/1FAIpQLSdL6XnoqNKTAw7dlsIr2ZZmRPtlLw-idLKWanRUaG1h56cebg/viewform?entry.1095270279=&entry.191341224=&entry.2101494904=Dúvida&entry.1095270279=&entry.950207260=&entry.237710686=&entry.1585267062=&entry.409012661= | G520: <-- clica copie e cole lá no navegador | N520: =$R$2&O520 -> https://docs.google.com/forms/d/e/1FAIpQLSdL6XnoqNKTAw7dlsIr2ZZmRPtlLw-idLKWanRUaG1h56cebg/viewform?entry.1095270279=&entry.191341224=&entry.2101494904=Dúvida&entry.1095270279=&entry.950207260=&entry.237710686=&entry.1585267062=&entry.409012661= | O520: =$Q$2&A520&$Q$3&C520&$Q$4&$S520&$Q$2&$Q$5&D520&$Q$6&D520&$T520&$U520&$V520&W520 -> entry.1095270279=&entry.191341224=&entry.2101494904=Dúvida&entry.1095270279=&entry.950207260=&entry.237710686=&entry.1585267062=&entry.409012661= | S520: =IF(COUNTIF($K$2:$K$21,D520)>0,"Execução&","Dúvida&") -> Dúvida& | T520: =IF(E520="BOM","&entry.2006968231=O agente demonstra conhecer o processo, mas aciona para validar a informação.","") | U520: =IF(E520="MEDIANO","&entry.2006968231=O agente demonstra não saber como conduzir a situação com o cliente&entry.2006968231=Falta de conhecimento da ferramenta","") | V520: =IF(E520="RUIM","&entry.2006968231=O agente demonstra não saber como conduzir a situação com o cliente&entry.2006968231=Falta de conhecimento da ferramenta&entry.2006968231=Não ter realizado a leitura no PIC ou CDA (Central de Ajuda Site Latam)&entry.2006968231=Não saber "&"interpretar a informação no PIC ou CDA (Central de Ajuda Site Latam)","") | W520: =$Z$2&H520&$Y$2&H520 -> &entry.1585267062=&entry.409012661=
F521: =N521 -> https://docs.google.com/forms/d/e/1FAIpQLSdL6XnoqNKTAw7dlsIr2ZZmRPtlLw-idLKWanRUaG1h56cebg/viewform?entry.1095270279=&entry.191341224=&entry.2101494904=Dúvida&entry.1095270279=&entry.950207260=&entry.237710686=&entry.1585267062=&entry.409012661= | G521: <-- clica copie e cole lá no navegador | N521: =$R$2&O521 -> https://docs.google.com/forms/d/e/1FAIpQLSdL6XnoqNKTAw7dlsIr2ZZmRPtlLw-idLKWanRUaG1h56cebg/viewform?entry.1095270279=&entry.191341224=&entry.2101494904=Dúvida&entry.1095270279=&entry.950207260=&entry.237710686=&entry.1585267062=&entry.409012661= | O521: =$Q$2&A521&$Q$3&C521&$Q$4&$S521&$Q$2&$Q$5&D521&$Q$6&D521&$T521&$U521&$V521&W521 -> entry.1095270279=&entry.191341224=&entry.2101494904=Dúvida&entry.1095270279=&entry.950207260=&entry.237710686=&entry.1585267062=&entry.409012661= | S521: =IF(COUNTIF($K$2:$K$21,D521)>0,"Execução&","Dúvida&") -> Dúvida& | T521: =IF(E521="BOM","&entry.2006968231=O agente demonstra conhecer o processo, mas aciona para validar a informação.","") | U521: =IF(E521="MEDIANO","&entry.2006968231=O agente demonstra não saber como conduzir a situação com o cliente&entry.2006968231=Falta de conhecimento da ferramenta","") | V521: =IF(E521="RUIM","&entry.2006968231=O agente demonstra não saber como conduzir a situação com o cliente&entry.2006968231=Falta de conhecimento da ferramenta&entry.2006968231=Não ter realizado a leitura no PIC ou CDA (Central de Ajuda Site Latam)&entry.2006968231=Não saber "&"interpretar a informação no PIC ou CDA (Central de Ajuda Site Latam)","") | W521: =$Z$2&H521&$Y$2&H521 -> &entry.1585267062=&entry.409012661=
F522: =N522 -> https://docs.google.com/forms/d/e/1FAIpQLSdL6XnoqNKTAw7dlsIr2ZZmRPtlLw-idLKWanRUaG1h56cebg/viewform?entry.1095270279=&entry.191341224=&entry.2101494904=Dúvida&entry.1095270279=&entry.950207260=&entry.237710686=&entry.1585267062=&entry.409012661= | G522: <-- clica copie e cole lá no navegador | N522: =$R$2&O522 -> https://docs.google.com/forms/d/e/1FAIpQLSdL6XnoqNKTAw7dlsIr2ZZmRPtlLw-idLKWanRUaG1h56cebg/viewform?entry.1095270279=&entry.191341224=&entry.2101494904=Dúvida&entry.1095270279=&entry.950207260=&entry.237710686=&entry.1585267062=&entry.409012661= | O522: =$Q$2&A522&$Q$3&C522&$Q$4&$S522&$Q$2&$Q$5&D522&$Q$6&D522&$T522&$U522&$V522&W522 -> entry.1095270279=&entry.191341224=&entry.2101494904=Dúvida&entry.1095270279=&entry.950207260=&entry.237710686=&entry.1585267062=&entry.409012661= | S522: =IF(COUNTIF($K$2:$K$21,D522)>0,"Execução&","Dúvida&") -> Dúvida& | T522: =IF(E522="BOM","&entry.2006968231=O agente demonstra conhecer o processo, mas aciona para validar a informação.","") | U522: =IF(E522="MEDIANO","&entry.2006968231=O agente demonstra não saber como conduzir a situação com o cliente&entry.2006968231=Falta de conhecimento da ferramenta","") | V522: =IF(E522="RUIM","&entry.2006968231=O agente demonstra não saber como conduzir a situação com o cliente&entry.2006968231=Falta de conhecimento da ferramenta&entry.2006968231=Não ter realizado a leitura no PIC ou CDA (Central de Ajuda Site Latam)&entry.2006968231=Não saber "&"interpretar a informação no PIC ou CDA (Central de Ajuda Site Latam)","") | W522: =$Z$2&H522&$Y$2&H522 -> &entry.1585267062=&entry.409012661=
F523: =N523 -> https://docs.google.com/forms/d/e/1FAIpQLSdL6XnoqNKTAw7dlsIr2ZZmRPtlLw-idLKWanRUaG1h56cebg/viewform?entry.1095270279=&entry.191341224=&entry.2101494904=Dúvida&entry.1095270279=&entry.950207260=&entry.237710686=&entry.1585267062=&entry.409012661= | G523: <-- clica copie e cole lá no navegador | N523: =$R$2&O523 -> https://docs.google.com/forms/d/e/1FAIpQLSdL6XnoqNKTAw7dlsIr2ZZmRPtlLw-idLKWanRUaG1h56cebg/viewform?entry.1095270279=&entry.191341224=&entry.2101494904=Dúvida&entry.1095270279=&entry.950207260=&entry.237710686=&entry.1585267062=&entry.409012661= | O523: =$Q$2&A523&$Q$3&C523&$Q$4&$S523&$Q$2&$Q$5&D523&$Q$6&D523&$T523&$U523&$V523&W523 -> entry.1095270279=&entry.191341224=&entry.2101494904=Dúvida&entry.1095270279=&entry.950207260=&entry.237710686=&entry.1585267062=&entry.409012661= | S523: =IF(COUNTIF($K$2:$K$21,D523)>0,"Execução&","Dúvida&") -> Dúvida& | T523: =IF(E523="BOM","&entry.2006968231=O agente demonstra conhecer o processo, mas aciona para validar a informação.","") | U523: =IF(E523="MEDIANO","&entry.2006968231=O agente demonstra não saber como conduzir a situação com o cliente&entry.2006968231=Falta de conhecimento da ferramenta","") | V523: =IF(E523="RUIM","&entry.2006968231=O agente demonstra não saber como conduzir a situação com o cliente&entry.2006968231=Falta de conhecimento da ferramenta&entry.2006968231=Não ter realizado a leitura no PIC ou CDA (Central de Ajuda Site Latam)&entry.2006968231=Não saber "&"interpretar a informação no PIC ou CDA (Central de Ajuda Site Latam)","") | W523: =$Z$2&H523&$Y$2&H523 -> &entry.1585267062=&entry.409012661=
... F1000: =N1000 -> https://docs.google.com/forms/d/e/1FAIpQLSdL6XnoqNKTAw7dlsIr2ZZmRPtlLw-idLKWanRUaG1h56cebg/viewform?entry.1095270279=&entry.191341224=&entry.2101494904=Dúvida&entry.1095270279=&entry.950207260=&entry.237710686=&entry.1585267062=&entry.409012661= | G1000: <-- clica copie e cole lá no navegador | N1000: =$R$2&O1000 -> https://docs.google.com/forms/d/e/1FAIpQLSdL6XnoqNKTAw7dlsIr2ZZmRPtlLw-idLKWanRUaG1h56cebg/viewform?entry.1095270279=&entry.191341224=&entry.2101494904=Dúvida&entry.1095270279=&entry.950207260=&entry.237710686=&entry.1585267062=&entry.409012661= | O1000: =$Q$2&A1000&$Q$3&C1000&$Q$4&$S1000&$Q$2&$Q$5&D1000&$Q$6&D1000&$T1000&$U1000&$V1000&W1000 -> entry.1095270279=&entry.191341224=&entry.2101494904=Dúvida&entry.1095270279=&entry.950207260=&entry.237710686=&entry.1585267062=&entry.409012661= | S1000: =IF(COUNTIF($K$2:$K$21,D1000)>0,"Execução&","Dúvida&") -> Dúvida& | T1000: =IF(E1000="BOM","&entry.2006968231=O agente demonstra conhecer o processo, mas aciona para validar a informação.","") | U1000: =IF(E1000="MEDIANO","&entry.2006968231=O agente demonstra não saber como conduzir a situação com o cliente&entry.2006968231=Falta de conhecimento da ferramenta","") | V1000: =IF(E1000="RUIM","&entry.2006968231=O agente demonstra não saber como conduzir a situação com o cliente&entry.2006968231=Falta de conhecimento da ferramenta&entry.2006968231=Não ter realizado a leitura no PIC ou CDA (Central de Ajuda Site Latam)&entry.2006968231=Não saber "&"interpretar a informação no PIC ou CDA (Central de Ajuda Site Latam)","") | W1000: =$Z$2&H1000&$Y$2&H1000 -> &entry.1585267062=&entry.409012661=
A1001: 453534 | B1001: Nomeome | C1001: queijo | D1001: Reembolso

Sheet Pagina de funcionário
A1: NOME | B1: SUPERVISOR | C1: BP | D1: HORÁRIO | E1: GERENTE | F1: LOCAL | G1: SAG | H1: Coluna 1 | I1: Coluna 2 | J1: Coluna 3 | K1: Coluna 4
L2: Adicione os dados dos funcionarios ao lado
